designs/sdram/sdram_ctrl.sv
`timescale 1ns / 1ps
//
// A minimal SDR SDRAM controller — the §8.20 test design.
//
// It drives a real JEDEC command bus (CS#/RAS#/CAS#/WE#, BA, A) through a
// scripted sequence, and the whole point of it is `VIOLATE`: with that
// parameter set, four of the delays are deliberately one cycle short of the
// MT48LC16M16A2 minimum — one from each of the four categories Prompt 11's
// acceptance criterion names (tRCD, tRP, tRFC, tFAW). With it clear the same
// RTL is conformant, so "no violations found" is as checkable as "four found".
//
// Written as a flat step counter rather than an FSM on purpose: the exact
// cycle numbers *are* the thing under test, so they should be readable
// straight off the source rather than inferred from state transitions.
//
// At the 100 MHz clock the testbench uses, one step is 10 ns, and the
// MT48LC16M16A2 -7E minima (packs/timing/mt48lc16m16a2.toml) become:
//
//     tRCD 20 ns -> 2 steps     tRP  20 ns -> 2 steps
//     tRAS 44 ns -> 5 steps     tRC  66 ns -> 7 steps
//     tRRD 15 ns -> 2 steps     tRFC 66 ns -> 7 steps
//     tFAW 75 ns -> 8 steps
//
// The four injected gaps are each exactly `- BUG` short of those. Every other
// gap in the sequence was checked by hand to sit clear of *every* constraint,
// so the run produces the four intended violations and no collateral ones —
// which is what makes the acceptance test able to assert an exact set.
//
module sdram_ctrl #(
    // 1 injects the timing bugs; 0 is the same controller, correct.
    parameter bit VIOLATE = 1'b1
) (
    input  logic        clk,
    input  logic        rst_n,

    output logic        cs_n,
    output logic        ras_n,
    output logic        cas_n,
    output logic        we_n,
    output logic [ 1:0] ba,
    output logic [12:0] a,

    output logic        done
);

  // ---- command encodings (JEDEC SDR SDRAM) --------------------------------
  // {cs_n, ras_n, cas_n, we_n}. CS# high is "deselected", which is the absence
  // of a command rather than a command of its own — hence no NOP row in the
  // protocol pack either.
  localparam logic [3:0] C_NOP       = 4'b1111;
  localparam logic [3:0] C_ACTIVATE  = 4'b0011;
  localparam logic [3:0] C_READ      = 4'b0101;
  localparam logic [3:0] C_WRITE     = 4'b0100;
  localparam logic [3:0] C_PRECHARGE = 4'b0010;
  localparam logic [3:0] C_REFRESH   = 4'b0001;

  // ---- datasheet minima, in clock cycles at 100 MHz -----------------------
  localparam int T_RCD = 2;
  localparam int T_RP  = 2;
  localparam int T_RRD = 2;
  localparam int T_RFC = 7;
  localparam int T_FAW = 8;

  // How long a row is held open before precharging. Comfortably above tRAS
  // (5 steps) so that tRAS never fires, and chosen so ACTIVATE -> PRECHARGE ->
  // ACTIVATE still clears tRC (7 steps) once the injected tRP bug has pulled
  // the second ACTIVATE one cycle earlier: 6 + 2 - 1 = 7. Getting this wrong
  // is how an injected tRP bug quietly becomes a tRC bug as well.
  localparam int ROW_OPEN = 6;

  // The injected bug: one cycle short of the minimum, in four places.
  localparam int BUG = VIOLATE ? 1 : 0;

  // ---- the scripted sequence ----------------------------------------------
  //
  //   VIOLATION 1 — tRCD: ACTIVATE b0 -> READ b0
  //   VIOLATION 2 — tRP : PRECHARGE b0 -> ACTIVATE b0
  //   VIOLATION 3 — tRFC: REFRESH -> ACTIVATE
  //   VIOLATION 4 — tFAW: the 4th ACTIVATE inside the rolling window
  //
  localparam int S_ACT0 = 4;                        // ACTIVATE b0, row 0x1A4
  localparam int S_RD0  = S_ACT0 + T_RCD - BUG;     // (1) tRCD
  localparam int S_PRE0 = S_ACT0 + ROW_OPEN;
  localparam int S_ACT1 = S_PRE0 + T_RP - BUG;      // (2) tRP
  localparam int S_PRE1 = S_ACT1 + ROW_OPEN;
  localparam int S_REF  = S_PRE1 + T_RP;
  localparam int S_ACT2 = S_REF + T_RFC - BUG;      // (3) tRFC
  localparam int S_WR   = S_ACT2 + T_RCD;           // conformant, exercises WRITE
  localparam int S_PRE2 = S_ACT2 + ROW_OPEN;

  // Four ACTIVATEs to four banks. The first three are tRRD apart; the fourth
  // lands inside tFAW of the first when the bug is injected, and just outside
  // it when it is not — while staying clear of tRRD either way.
  localparam int S_FAW0 = S_PRE2 + T_RP;
  localparam int S_FAW1 = S_FAW0 + T_RRD;
  localparam int S_FAW2 = S_FAW1 + T_RRD;
  localparam int S_FAW3 = S_FAW0 + T_FAW - BUG;     // (4) tFAW

  localparam int N_STEPS = S_FAW3 + 12;

  logic [7:0]  step;
  logic [3:0]  cmd;
  logic [1:0]  cmd_ba;
  logic [12:0] cmd_a;

  assign {cs_n, ras_n, cas_n, we_n} = cmd;
  assign ba   = cmd_ba;
  assign a    = cmd_a;
  assign done = (step >= N_STEPS[7:0]);

  always_comb begin
    cmd    = C_NOP;
    cmd_ba = 2'd0;
    cmd_a  = 13'd0;
    case (step)
      S_ACT0:  begin cmd = C_ACTIVATE;  cmd_ba = 2'd0; cmd_a = 13'h1A4; end
      S_RD0:   begin cmd = C_READ;      cmd_ba = 2'd0; cmd_a = 13'h030; end
      S_PRE0:  begin cmd = C_PRECHARGE; cmd_ba = 2'd0; cmd_a = 13'd0;   end
      S_ACT1:  begin cmd = C_ACTIVATE;  cmd_ba = 2'd0; cmd_a = 13'h0C8; end
      S_PRE1:  begin cmd = C_PRECHARGE; cmd_ba = 2'd0; cmd_a = 13'd0;   end
      S_REF:   begin cmd = C_REFRESH;                                    end
      S_ACT2:  begin cmd = C_ACTIVATE;  cmd_ba = 2'd1; cmd_a = 13'h200; end
      S_WR:    begin cmd = C_WRITE;     cmd_ba = 2'd1; cmd_a = 13'h018; end
      S_PRE2:  begin cmd = C_PRECHARGE; cmd_ba = 2'd1; cmd_a = 13'd0;   end
      S_FAW0:  begin cmd = C_ACTIVATE;  cmd_ba = 2'd0; cmd_a = 13'h010; end
      S_FAW1:  begin cmd = C_ACTIVATE;  cmd_ba = 2'd1; cmd_a = 13'h011; end
      S_FAW2:  begin cmd = C_ACTIVATE;  cmd_ba = 2'd2; cmd_a = 13'h012; end
      S_FAW3:  begin cmd = C_ACTIVATE;  cmd_ba = 2'd3; cmd_a = 13'h013; end
      default: ;
    endcase
  end

  always_ff @(posedge clk or negedge rst_n) begin
    if (!rst_n) step <= 8'd0;
    else if (step < N_STEPS[7:0]) step <= step + 8'd1;
  end

endmodule

designs/sdram/tb_sdram.sv
`timescale 1ns / 1ps
//
// The §8.20 test design: a minimal SDR SDRAM controller driving a real JEDEC
// command bus, with four timing violations injected — one from each category
// Prompt 11's acceptance criterion names.
//
//     iverilog -g2012 -o sim.vvp *.sv                  && vvp sim.vvp
//         -> dump.vcd     tRCD, tRP, tRFC and tFAW each violated once
//
//     iverilog -g2012 -DNO_VIOLATION -o sim_ok.vvp *.sv && vvp sim_ok.vvp
//         -> dump_ok.vcd  the same RTL, conformant
//
// A compile-time define rather than a runtime flag, for the reason
// designs/deadlock uses one too: the bug is then a property of the elaborated
// design, so it is visible in the graph and reachable from `why`.
//
// 100 MHz, so one clock is 10 ns and the datasheet's nanosecond minima map to
// whole cycles — see sdram_ctrl.sv for the arithmetic. There is no SDRAM model
// on the other end: §8.20 analyses the *command bus*, so the controller
// driving it is the entire device under test.
//
module tb_sdram;

`ifdef NO_VIOLATION
  localparam bit VIOLATE = 1'b0;
`else
  localparam bit VIOLATE = 1'b1;
`endif

  logic clk = 1'b0;
  logic rst_n = 1'b0;

  always #5 clk = ~clk;  // 100 MHz

  logic        cs_n, ras_n, cas_n, we_n;
  logic [ 1:0] ba;
  logic [12:0] a;
  logic        done;

  sdram_ctrl #(
      .VIOLATE(VIOLATE)
  ) ctrl (
      .clk  (clk),
      .rst_n(rst_n),
      .cs_n (cs_n),
      .ras_n(ras_n),
      .cas_n(cas_n),
      .we_n (we_n),
      .ba   (ba),
      .a    (a),
      .done (done)
  );

  initial begin
`ifdef NO_VIOLATION
    $dumpfile("dump_ok.vcd");
`else
    $dumpfile("dump.vcd");
`endif
    $dumpvars(0, tb_sdram);

    repeat (4) @(posedge clk);
    rst_n <= 1'b1;

    wait (done);
    repeat (4) @(posedge clk);
    $display("[tb_sdram] sequence complete (VIOLATE=%0b)", VIOLATE);
    $finish;
  end

endmodule

designs/sdram/dump.vcd
$date
	Thu Aug 06 16:26:27 2026
$end
$version
	Icarus Verilog
$end
$timescale
	1ps
$end
$scope module tb_sdram $end
$var wire 1 ! we_n $end
$var wire 1 " ras_n $end
$var wire 1 # done $end
$var wire 1 $ cs_n $end
$var wire 1 % cas_n $end
$var wire 2 & ba [1:0] $end
$var wire 13 ' a [12:0] $end
$var parameter 1 ( VIOLATE $end
$var reg 1 ) clk $end
$var reg 1 * rst_n $end
$scope module ctrl $end
$var wire 13 + a [12:0] $end
$var wire 2 , ba [1:0] $end
$var wire 1 ) clk $end
$var wire 1 * rst_n $end
$var wire 1 ! we_n $end
$var wire 1 " ras_n $end
$var wire 1 # done $end
$var wire 1 $ cs_n $end
$var wire 1 % cas_n $end
$var parameter 32 - BUG $end
$var parameter 4 . C_ACTIVATE $end
$var parameter 4 / C_NOP $end
$var parameter 4 0 C_PRECHARGE $end
$var parameter 4 1 C_READ $end
$var parameter 4 2 C_REFRESH $end
$var parameter 4 3 C_WRITE $end
$var parameter 32 4 N_STEPS $end
$var parameter 32 5 ROW_OPEN $end
$var parameter 32 6 S_ACT0 $end
$var parameter 32 7 S_ACT1 $end
$var parameter 32 8 S_ACT2 $end
$var parameter 32 9 S_FAW0 $end
$var parameter 32 : S_FAW1 $end
$var parameter 32 ; S_FAW2 $end
$var parameter 32 < S_FAW3 $end
$var parameter 32 = S_PRE0 $end
$var parameter 32 > S_PRE1 $end
$var parameter 32 ? S_PRE2 $end
$var parameter 32 @ S_RD0 $end
$var parameter 32 A S_REF $end
$var parameter 32 B S_WR $end
$var parameter 32 C T_FAW $end
$var parameter 32 D T_RCD $end
$var parameter 32 E T_RFC $end
$var parameter 32 F T_RP $end
$var parameter 32 G T_RRD $end
$var parameter 1 H VIOLATE $end
$var reg 4 I cmd [3:0] $end
$var reg 13 J cmd_a [12:0] $end
$var reg 2 K cmd_ba [1:0] $end
$var reg 8 L step [7:0] $end
$upscope $end
$upscope $end
$enddefinitions $end
$comment Show the parameter values. $end
$dumpall
1H
b10 G
b10 F
b111 E
b10 D
b1000 C
b11011 B
b10011 A
b101 @
b11111 ?
b10001 >
b1010 =
b101000 <
b100101 ;
b100011 :
b100001 9
b11001 8
b1011 7
b100 6
b110 5
b110100 4
b100 3
b1 2
b101 1
b10 0
b1111 /
b11 .
b1 -
1(
$end
#0
$dumpvars
bx L
b0 K
b0 J
b1111 I
b0 ,
b0 +
0*
0)
b0 '
b0 &
1%
1$
x#
1"
1!
$end
#5000
0#
b0 L
1)
#10000
0)
#15000
1)
#20000
0)
#25000
1)
#30000
0)
#35000
1*
1)
#40000
0)
#45000
b1 L
1)
#50000
0)
#55000
b10 L
1)
#60000
0)
#65000
b11 L
1)
#70000
0)
#75000
0$
0"
b110100100 '
b110100100 +
b110100100 J
b11 I
b100 L
1)
#80000
0)
#85000
0%
1"
b110000 '
b110000 +
b110000 J
b101 I
b101 L
1)
#90000
0)
#95000
1$
1%
b0 '
b0 +
b0 J
b1111 I
b110 L
1)
#100000
0)
#105000
b111 L
1)
#110000
0)
#115000
b1000 L
1)
#120000
0)
#125000
b1001 L
1)
#130000
0)
#135000
0$
0"
0!
b10 I
b1010 L
1)
#140000
0)
#145000
1!
b11001000 '
b11001000 +
b11001000 J
b11 I
b1011 L
1)
#150000
0)
#155000
1$
1"
b0 '
b0 +
b0 J
b1111 I
b1100 L
1)
#160000
0)
#165000
b1101 L
1)
#170000
0)
#175000
b1110 L
1)
#180000
0)
#185000
b1111 L
1)
#190000
0)
#195000
b10000 L
1)
#200000
0)
#205000
0$
0"
0!
b10 I
b10001 L
1)
#210000
0)
#215000
1$
1"
1!
b1111 I
b10010 L
1)
#220000
0)
#225000
0$
0"
0%
b1 I
b10011 L
1)
#230000
0)
#235000
1$
1"
1%
b1111 I
b10100 L
1)
#240000
0)
#245000
b10101 L
1)
#250000
0)
#255000
b10110 L
1)
#260000
0)
#265000
b10111 L
1)
#270000
0)
#275000
b11000 L
1)
#280000
0)
#285000
0$
0"
b1000000000 '
b1000000000 +
b1000000000 J
b1 &
b1 ,
b1 K
b11 I
b11001 L
1)
#290000
0)
#295000
1$
1"
b0 '
b0 +
b0 J
b0 &
b0 ,
b0 K
b1111 I
b11010 L
1)
#300000
0)
#305000
0$
0%
0!
b11000 '
b11000 +
b11000 J
b1 &
b1 ,
b1 K
b100 I
b11011 L
1)
#310000
0)
#315000
1$
1%
1!
b0 '
b0 +
b0 J
b0 &
b0 ,
b0 K
b1111 I
b11100 L
1)
#320000
0)
#325000
b11101 L
1)
#330000
0)
#335000
b11110 L
1)
#340000
0)
#345000
0$
0"
0!
b1 &
b1 ,
b1 K
b10 I
b11111 L
1)
#350000
0)
#355000
1$
1"
1!
b0 &
b0 ,
b0 K
b1111 I
b100000 L
1)
#360000
0)
#365000
0$
0"
b10000 '
b10000 +
b10000 J
b11 I
b100001 L
1)
#370000
0)
#375000
1$
1"
b0 '
b0 +
b0 J
b1111 I
b100010 L
1)
#380000
0)
#385000
0$
0"
b10001 '
b10001 +
b10001 J
b1 &
b1 ,
b1 K
b11 I
b100011 L
1)
#390000
0)
#395000
1$
1"
b0 '
b0 +
b0 J
b0 &
b0 ,
b0 K
b1111 I
b100100 L
1)
#400000
0)
#405000
0$
0"
b10010 '
b10010 +
b10010 J
b10 &
b10 ,
b10 K
b11 I
b100101 L
1)
#410000
0)
#415000
1$
1"
b0 '
b0 +
b0 J
b0 &
b0 ,
b0 K
b1111 I
b100110 L
1)
#420000
0)
#425000
b100111 L
1)
#430000
0)
#435000
0$
0"
b10011 '
b10011 +
b10011 J
b11 &
b11 ,
b11 K
b11 I
b101000 L
1)
#440000
0)
#445000
1$
1"
b0 '
b0 +
b0 J
b0 &
b0 ,
b0 K
b1111 I
b101001 L
1)
#450000
0)
#455000
b101010 L
1)
#460000
0)
#465000
b101011 L
1)
#470000
0)
#475000
b101100 L
1)
#480000
0)
#485000
b101101 L
1)
#490000
0)
#495000
b101110 L
1)
#500000
0)
#505000
b101111 L
1)
#510000
0)
#515000
b110000 L
1)
#520000
0)
#525000
b110001 L
1)
#530000
0)
#535000
b110010 L
1)
#540000
0)
#545000
b110011 L
1)
#550000
0)
#555000
1#
b110100 L
1)
