designs/cpu_top/cpu_top.sv
`timescale 1ns / 1ps

// A two-stage RV32I subset — the realistic design of §14.1.
//
// Small on purpose, but it has the three structures that make a CPU hard to
// debug and that no other reference design here contains:
//
//   * a **register file read by a dynamic index** (`regfile[rs1]`), which is
//     §5.6's own example and the case where a causal chain has to jump back in
//     time to the instruction that wrote the value;
//   * a **pipeline register**, so a value read in one cycle was computed in the
//     one before it (§5.5's NBA rule, on a design where getting it wrong is not
//     obvious);
//   * **three deliberately injected bugs**, listed in README.md with the exact
//     root cause each one has. They are injected by this project, not taken
//     from anyone's bug list.
//
// Every bug is behind a `define` so the design can be built correct or broken
// from the same source: `-DFIX_ALL` makes it a clean CPU.

module cpu_top #(
    parameter int IMEM_WORDS = 32,
    parameter int DMEM_WORDS = 32
) (
    input  logic        clk,
    input  logic        rst_n,
    output logic [31:0] pc,
    output logic [31:0] instr,
    output logic [31:0] wb_data,
    output logic [4:0]  wb_addr,
    output logic        wb_en,
    output logic        retire_valid
);
    // ---- architectural state ------------------------------------------
    logic [31:0] regfile [32];
    logic [31:0] imem    [IMEM_WORDS];
    logic [31:0] dmem    [DMEM_WORDS];

    // ---- fetch ---------------------------------------------------------
    logic [31:0] pc_q;
    assign pc    = pc_q;
    assign instr = imem[pc_q[6:2]];

    localparam logic [6:0] OP_IMM = 7'b0010011;
    localparam logic [6:0] OP_REG = 7'b0110011;
    localparam logic [6:0] OP_LOAD = 7'b0000011;
    localparam logic [6:0] OP_STORE = 7'b0100011;
    localparam logic [6:0] OP_BRANCH = 7'b1100011;

    // ---- decode --------------------------------------------------------
    logic [6:0]  opcode;
    logic [4:0]  rs1, rs2, rd;
    logic [2:0]  funct3;
    logic [31:0] imm_i, imm_s, imm_b;

    assign opcode = instr[6:0];
    assign rd     = instr[11:7];
    assign funct3 = instr[14:12];
    assign rs1    = instr[19:15];
    assign rs2    = instr[24:20];
    assign imm_i  = {{20{instr[31]}}, instr[31:20]};
    assign imm_s  = {{20{instr[31]}}, instr[31:25], instr[11:7]};
    assign imm_b  = {{20{instr[31]}}, instr[7], instr[30:25], instr[11:8], 1'b0};

    // §5.6: two dynamically indexed reads. This is the whole reason this design
    // exists — asking why `rs1_data` is wrong has to resolve the index, name
    // one word, and jump to the cycle that wrote it.
    logic [31:0] rs1_data, rs2_data;
    assign rs1_data = regfile[rs1];
    assign rs2_data = regfile[rs2];

    // ---- execute -------------------------------------------------------
    logic [31:0] alu_b, alu_out;
    // A store carries its offset in the S-type fields, not the I-type ones —
    // using `imm_i` here would displace every store by a few words, which is a
    // bug this design is *not* trying to inject.
    always_comb begin
        if (opcode == OP_REG || opcode == OP_BRANCH) alu_b = rs2_data;
        else if (opcode == OP_STORE)                 alu_b = imm_s;
        else                                         alu_b = imm_i;
    end

    always_comb begin
        unique case (funct3)
            3'b000:  alu_out = (opcode == OP_REG && instr[30]) ? rs1_data - alu_b
                                                              : rs1_data + alu_b;
            3'b111:  alu_out = rs1_data & alu_b;
            3'b110:  alu_out = rs1_data | alu_b;
            default: alu_out = rs1_data + alu_b;
        endcase
    end

    logic take_branch;
`ifdef BUG_BRANCH_POLARITY
    // BUG 2 — BNE is decoded with the polarity of BEQ, so the loop in the test
    // program exits one iteration early. Root cause: this line.
    assign take_branch = (opcode == OP_BRANCH) && (rs1_data == rs2_data);
`else
    assign take_branch = (opcode == OP_BRANCH) &&
                         ((funct3 == 3'b000) ? (rs1_data == rs2_data)
                                             : (rs1_data != rs2_data));
`endif

    // ---- memory --------------------------------------------------------
    logic [31:0] mem_addr, load_data;
    assign mem_addr  = alu_out;
    assign load_data = dmem[mem_addr[6:2]];

    // ---- write-back ----------------------------------------------------
    assign wb_addr = rd;
    assign wb_data = (opcode == OP_LOAD) ? load_data : alu_out;
`ifdef BUG_X0_WRITABLE
    // BUG 1 — x0 is not hardwired to zero, so the first `addi x0, x0, 0` in
    // the program leaves a value behind and every later read of x0 is wrong.
    // Root cause: the missing `rd != 0` term here.
    assign wb_en = (opcode == OP_IMM || opcode == OP_REG || opcode == OP_LOAD);
`else
    assign wb_en = (opcode == OP_IMM || opcode == OP_REG || opcode == OP_LOAD) && (rd != 5'd0);
`endif

    assign retire_valid = (opcode != 7'b0);

    // ---- sequential ----------------------------------------------------
    always_ff @(posedge clk or negedge rst_n) begin
        if (!rst_n) begin
            pc_q <= 32'd0;
        end else if (take_branch) begin
            pc_q <= pc_q + imm_b;
        end else begin
            pc_q <= pc_q + 32'd4;
        end
    end

    always_ff @(posedge clk or negedge rst_n) begin
        if (!rst_n) begin
            for (int i = 0; i < 32; i++) regfile[i] <= 32'd0;
        end else if (wb_en) begin
            regfile[wb_addr] <= wb_data;
        end
    end

    always_ff @(posedge clk) begin
        if (rst_n && opcode == OP_STORE) begin
`ifdef BUG_STORE_INDEX
            // BUG 3 — the store uses the *byte* address as a word index, so it
            // writes four words too far and the load that follows reads a word
            // that was never written. Root cause: the missing `[6:2]` slice.
            dmem[mem_addr[4:0]] <= rs2_data;
`else
            dmem[mem_addr[6:2]] <= rs2_data;
`endif
        end
    end
endmodule

designs/cpu_top/tb_cpu_top.sv
`timescale 1ns / 1ps

// Drives `cpu_top` through a short RV32I program and dumps the register file
// word by word — Icarus needs an explicit `$dumpvars` per element for unpacked
// arrays (§5.6), and without it the regfile is invisible to the tool.
module tb_cpu_top;
    logic clk = 1'b0;
    logic rst_n = 1'b0;

    logic [31:0] pc, instr, wb_data;
    logic [4:0]  wb_addr;
    logic        wb_en, retire_valid;

    cpu_top dut (
        .clk(clk),
        .rst_n(rst_n),
        .pc(pc),
        .instr(instr),
        .wb_data(wb_data),
        .wb_addr(wb_addr),
        .wb_en(wb_en),
        .retire_valid(retire_valid)
    );

    always #5 clk = ~clk;

    // A program that exercises every injected bug:
    //
    //   0: addi x0, x0, 7      x0 must stay 0 (BUG_X0_WRITABLE)
    //   4: addi x1, x0, 5      x1 = 5      — reads x0, so it inherits bug 1
    //   8: addi x2, x0, 3      x2 = 3
    //   c: add  x3, x1, x2     x3 = 8      — two regfile reads at once
    //  10: addi x4, x0, 64     x4 = 64     — a word address for the store
    //  14: sw   x3, 0(x4)      dmem[16] = 8 (BUG_STORE_INDEX)
    //  18: lw   x5, 0(x4)      x5 = 8      — the load that reads it back
    //  1c: addi x6, x0, 1      x6 = 1
    //  20: bne  x5, x6, -4     loop while x5 != x6 (BUG_BRANCH_POLARITY)
    //  24: addi x7, x0, 9
    initial begin
        dut.imem[0]  = 32'h00700013;  // addi x0, x0, 7
        dut.imem[1]  = 32'h00500093;  // addi x1, x0, 5
        dut.imem[2]  = 32'h00300113;  // addi x2, x0, 3
        dut.imem[3]  = 32'h002081b3;  // add  x3, x1, x2
        dut.imem[4]  = 32'h04000213;  // addi x4, x0, 64
        dut.imem[5]  = 32'h00322023;  // sw   x3, 0(x4)
        dut.imem[6]  = 32'h00022283;  // lw   x5, 0(x4)
        dut.imem[7]  = 32'h00800313;  // addi x6, x0, 8
        dut.imem[8]  = 32'hfe629ee3;  // bne  x5, x6, -4
        dut.imem[9]  = 32'h00900393;  // addi x7, x0, 9
        for (int i = 10; i < 32; i++) dut.imem[i] = 32'h00000013;  // nop
        for (int i = 0; i < 32; i++) dut.dmem[i] = 32'h0;
    end

    initial begin
        $dumpfile("dump.vcd");
        $dumpvars(0, tb_cpu_top);
`ifdef __ICARUS__
        // §5.6: unpacked-array elements need naming one by one, and only Icarus
        // accepts it. Eight words is enough for the program above and keeps the
        // dump small.
        $dumpvars(1, dut.regfile[0], dut.regfile[1], dut.regfile[2], dut.regfile[3],
                     dut.regfile[4], dut.regfile[5], dut.regfile[6], dut.regfile[7]);
        // Both ends of the store bug: `sw x3, 0(x4)` with x4 = 64 should write
        // word 16, and the broken index writes word 0 instead.
        $dumpvars(1, dut.dmem[0], dut.dmem[1], dut.dmem[2], dut.dmem[3]);
        $dumpvars(1, dut.dmem[16], dut.dmem[17], dut.dmem[18]);
`endif
        #12 rst_n = 1'b1;
        #400 $finish;
    end
endmodule

designs/cpu_top/dump.vcd
$date
	Sat Aug 15 10:24:43 2026
$end
$version
	Icarus Verilog
$end
$timescale
	1ps
$end
$scope module tb_cpu_top $end
$var wire 1 ! wb_en $end
$var wire 32 " wb_data [31:0] $end
$var wire 5 # wb_addr [4:0] $end
$var wire 1 $ retire_valid $end
$var wire 32 % pc [31:0] $end
$var wire 32 & instr [31:0] $end
$var reg 1 ' clk $end
$var reg 1 ( rst_n $end
$scope module dut $end
$var wire 1 ' clk $end
$var wire 32 ) instr [31:0] $end
$var wire 32 * load_data [31:0] $end
$var wire 32 + mem_addr [31:0] $end
$var wire 32 , pc [31:0] $end
$var wire 32 - rs1_data [31:0] $end
$var wire 32 . rs2_data [31:0] $end
$var wire 1 ( rst_n $end
$var wire 1 / take_branch $end
$var wire 5 0 wb_addr [4:0] $end
$var wire 1 ! wb_en $end
$var wire 32 1 wb_data [31:0] $end
$var wire 5 2 rs2 [4:0] $end
$var wire 5 3 rs1 [4:0] $end
$var wire 1 $ retire_valid $end
$var wire 5 4 rd [4:0] $end
$var wire 7 5 opcode [6:0] $end
$var wire 32 6 imm_s [31:0] $end
$var wire 32 7 imm_i [31:0] $end
$var wire 32 8 imm_b [31:0] $end
$var wire 3 9 funct3 [2:0] $end
$var parameter 32 : DMEM_WORDS $end
$var parameter 32 ; IMEM_WORDS $end
$var parameter 7 < OP_BRANCH $end
$var parameter 7 = OP_IMM $end
$var parameter 7 > OP_LOAD $end
$var parameter 7 ? OP_REG $end
$var parameter 7 @ OP_STORE $end
$var reg 32 A alu_b [31:0] $end
$var reg 32 B alu_out [31:0] $end
$var reg 32 C pc_q [31:0] $end
$scope begin $ivl_for_loop0 $end
$var integer 32 D i [31:0] $end
$upscope $end
$upscope $end
$scope begin $ivl_for_loop1 $end
$var integer 32 E i [31:0] $end
$upscope $end
$scope begin $ivl_for_loop2 $end
$var integer 32 F i [31:0] $end
$upscope $end
$upscope $end
$scope module tb_cpu_top $end
$scope module dut $end
$var reg 32 G \regfile[0] [31:0] $end
$upscope $end
$upscope $end
$scope module tb_cpu_top $end
$scope module dut $end
$var reg 32 H \regfile[1] [31:0] $end
$upscope $end
$upscope $end
$scope module tb_cpu_top $end
$scope module dut $end
$var reg 32 I \regfile[2] [31:0] $end
$upscope $end
$upscope $end
$scope module tb_cpu_top $end
$scope module dut $end
$var reg 32 J \regfile[3] [31:0] $end
$upscope $end
$upscope $end
$scope module tb_cpu_top $end
$scope module dut $end
$var reg 32 K \regfile[4] [31:0] $end
$upscope $end
$upscope $end
$scope module tb_cpu_top $end
$scope module dut $end
$var reg 32 L \regfile[5] [31:0] $end
$upscope $end
$upscope $end
$scope module tb_cpu_top $end
$scope module dut $end
$var reg 32 M \regfile[6] [31:0] $end
$upscope $end
$upscope $end
$scope module tb_cpu_top $end
$scope module dut $end
$var reg 32 N \regfile[7] [31:0] $end
$upscope $end
$upscope $end
$scope module tb_cpu_top $end
$scope module dut $end
$var reg 32 O \dmem[0] [31:0] $end
$upscope $end
$upscope $end
$scope module tb_cpu_top $end
$scope module dut $end
$var reg 32 P \dmem[1] [31:0] $end
$upscope $end
$upscope $end
$scope module tb_cpu_top $end
$scope module dut $end
$var reg 32 Q \dmem[2] [31:0] $end
$upscope $end
$upscope $end
$scope module tb_cpu_top $end
$scope module dut $end
$var reg 32 R \dmem[3] [31:0] $end
$upscope $end
$upscope $end
$scope module tb_cpu_top $end
$scope module dut $end
$var reg 32 S \dmem[16] [31:0] $end
$upscope $end
$upscope $end
$scope module tb_cpu_top $end
$scope module dut $end
$var reg 32 T \dmem[17] [31:0] $end
$upscope $end
$upscope $end
$scope module tb_cpu_top $end
$scope module dut $end
$var reg 32 U \dmem[18] [31:0] $end
$upscope $end
$upscope $end
$enddefinitions $end
$comment Show the parameter values. $end
$dumpall
b100011 @
b110011 ?
b11 >
b10011 =
b1100011 <
b100000 ;
b100000 :
$end
#0
$dumpvars
b0 U
b0 T
b0 S
b0 R
b0 Q
b0 P
b0 O
bx N
bx M
bx L
bx K
bx J
bx I
bx H
bx G
b100000 F
b100000 E
b0 D
bx C
bx B
bx A
bx 9
bx0 8
bx 7
bx 6
bx 5
bx 4
bx 3
bx 2
bx 1
bx 0
x/
bx .
bx -
bx ,
bx +
bx *
bx )
0(
0'
bx &
bx %
x$
bx #
bx "
x!
$end
#5000
b111 "
b111 1
b0 *
b111 +
b111 B
0/
0!
b111 A
1$
b10011 5
b0 #
b0 0
b0 4
b0 9
b0 -
b0 3
b0 .
b111 2
b111 7
b0 6
b0 8
b11100000000000000010011 &
b11100000000000000010011 )
b0 N
b0 M
b0 L
b0 K
b0 J
b0 I
b0 H
b0 G
b0 %
b0 ,
b0 C
b100000 D
1'
#10000
0'
#12000
1(
#15000
b101 "
b101 1
b101 +
b101 B
1!
b101 A
b1 #
b1 0
b1 4
b101 2
b101 7
b1 6
b100000000000 8
b10100000000000010010011 &
b10100000000000010010011 )
b100 %
b100 ,
b100 C
1'
#20000
0'
#25000
b11 "
b11 1
b11 +
b11 B
b11 A
b10 #
b10 0
b10 4
b11 2
b11 7
b10 6
b10 8
b1100000000000100010011 &
b1100000000000100010011 )
b101 H
b1000 %
b1000 ,
b1000 C
1'
#30000
0'
#35000
b1000 "
b1000 1
b1000 +
b1000 B
b110011 5
b11 #
b11 0
b11 4
b101 -
b1 3
b11 .
b10 2
b10 7
b11 6
b100000000010 8
b1000001000000110110011 &
b1000001000000110110011 )
b1100 %
b1100 ,
b1100 C
b11 I
1'
#40000
0'
#45000
b1000000 "
b1000000 1
b1000000 A
b1000000 +
b1000000 B
b10011 5
b100 #
b100 0
b100 4
b0 -
b0 3
b0 .
b0 2
b1000000 7
b1000100 6
b1000100 8
b100000000000000001000010011 &
b100000000000000001000010011 )
b1000 J
b10000 %
b10000 ,
b10000 C
1'
#50000
0'
#55000
b1000000 "
b1000000 1
0!
b0 A
b1000000 +
b1000000 B
b100011 5
b0 #
b0 0
b0 4
b10 9
b1000000 -
b100 3
b1000 .
b11 2
b11 7
b0 6
b0 8
b1100100010000000100011 &
b1100100010000000100011 )
b10100 %
b10100 ,
b10100 C
b1000000 K
1'
#60000
0'
#65000
1!
b0 "
b0 1
b11 5
b101 #
b101 0
b101 4
b0 .
b0 2
b0 7
b101 6
b100000000100 8
b100010001010000011 &
b100010001010000011 )
b1000 O
b11000 %
b11000 ,
b11000 C
1'
#70000
0'
#75000
b1000 "
b1000 1
1!
b0 *
b1000 A
b1000 +
b1000 B
b10011 5
b110 #
b110 0
b110 4
b0 9
b0 -
b0 3
b1000 2
b1000 7
b110 6
b110 8
b100000000000001100010011 &
b100000000000001100010011 )
b11100 %
b11100 ,
b11100 C
b0 L
1'
#80000
0'
#85000
0!
1/
b1100011 5
b11101 #
b11101 0
b11101 4
b1 9
b101 3
b1000 .
b110 2
b11111111111111111111111111100110 7
b11111111111111111111111111111101 6
b11111111111111111111111111111100 8
b11111110011000101001111011100011 &
b11111110011000101001111011100011 )
b1000 M
b100000 %
b100000 ,
b100000 C
1'
#90000
0'
#95000
1!
0/
b10011 5
b110 #
b110 0
b110 4
b0 9
b0 3
b0 .
b1000 2
b1000 7
b110 6
b110 8
b100000000000001100010011 &
b100000000000001100010011 )
b11100 %
b11100 ,
b11100 C
1'
#100000
0'
#105000
0!
1/
b1100011 5
b11101 #
b11101 0
b11101 4
b1 9
b101 3
b1000 .
b110 2
b11111111111111111111111111100110 7
b11111111111111111111111111111101 6
b11111111111111111111111111111100 8
b11111110011000101001111011100011 &
b11111110011000101001111011100011 )
b1000 M
b100000 %
b100000 ,
b100000 C
1'
#110000
0'
#115000
1!
0/
b10011 5
b110 #
b110 0
b110 4
b0 9
b0 3
b0 .
b1000 2
b1000 7
b110 6
b110 8
b100000000000001100010011 &
b100000000000001100010011 )
b11100 %
b11100 ,
b11100 C
1'
#120000
0'
#125000
0!
1/
b1100011 5
b11101 #
b11101 0
b11101 4
b1 9
b101 3
b1000 .
b110 2
b11111111111111111111111111100110 7
b11111111111111111111111111111101 6
b11111111111111111111111111111100 8
b11111110011000101001111011100011 &
b11111110011000101001111011100011 )
b1000 M
b100000 %
b100000 ,
b100000 C
1'
#130000
0'
#135000
1!
0/
b10011 5
b110 #
b110 0
b110 4
b0 9
b0 3
b0 .
b1000 2
b1000 7
b110 6
b110 8
b100000000000001100010011 &
b100000000000001100010011 )
b11100 %
b11100 ,
b11100 C
1'
#140000
0'
#145000
0!
1/
b1100011 5
b11101 #
b11101 0
b11101 4
b1 9
b101 3
b1000 .
b110 2
b11111111111111111111111111100110 7
b11111111111111111111111111111101 6
b11111111111111111111111111111100 8
b11111110011000101001111011100011 &
b11111110011000101001111011100011 )
b1000 M
b100000 %
b100000 ,
b100000 C
1'
#150000
0'
#155000
1!
0/
b10011 5
b110 #
b110 0
b110 4
b0 9
b0 3
b0 .
b1000 2
b1000 7
b110 6
b110 8
b100000000000001100010011 &
b100000000000001100010011 )
b11100 %
b11100 ,
b11100 C
1'
#160000
0'
#165000
0!
1/
b1100011 5
b11101 #
b11101 0
b11101 4
b1 9
b101 3
b1000 .
b110 2
b11111111111111111111111111100110 7
b11111111111111111111111111111101 6
b11111111111111111111111111111100 8
b11111110011000101001111011100011 &
b11111110011000101001111011100011 )
b1000 M
b100000 %
b100000 ,
b100000 C
1'
#170000
0'
#175000
1!
0/
b10011 5
b110 #
b110 0
b110 4
b0 9
b0 3
b0 .
b1000 2
b1000 7
b110 6
b110 8
b100000000000001100010011 &
b100000000000001100010011 )
b11100 %
b11100 ,
b11100 C
1'
#180000
0'
#185000
0!
1/
b1100011 5
b11101 #
b11101 0
b11101 4
b1 9
b101 3
b1000 .
b110 2
b11111111111111111111111111100110 7
b11111111111111111111111111111101 6
b11111111111111111111111111111100 8
b11111110011000101001111011100011 &
b11111110011000101001111011100011 )
b1000 M
b100000 %
b100000 ,
b100000 C
1'
#190000
0'
#195000
1!
0/
b10011 5
b110 #
b110 0
b110 4
b0 9
b0 3
b0 .
b1000 2
b1000 7
b110 6
b110 8
b100000000000001100010011 &
b100000000000001100010011 )
b11100 %
b11100 ,
b11100 C
1'
#200000
0'
#205000
0!
1/
b1100011 5
b11101 #
b11101 0
b11101 4
b1 9
b101 3
b1000 .
b110 2
b11111111111111111111111111100110 7
b11111111111111111111111111111101 6
b11111111111111111111111111111100 8
b11111110011000101001111011100011 &
b11111110011000101001111011100011 )
b1000 M
b100000 %
b100000 ,
b100000 C
1'
#210000
0'
#215000
1!
0/
b10011 5
b110 #
b110 0
b110 4
b0 9
b0 3
b0 .
b1000 2
b1000 7
b110 6
b110 8
b100000000000001100010011 &
b100000000000001100010011 )
b11100 %
b11100 ,
b11100 C
1'
#220000
0'
#225000
0!
1/
b1100011 5
b11101 #
b11101 0
b11101 4
b1 9
b101 3
b1000 .
b110 2
b11111111111111111111111111100110 7
b11111111111111111111111111111101 6
b11111111111111111111111111111100 8
b11111110011000101001111011100011 &
b11111110011000101001111011100011 )
b1000 M
b100000 %
b100000 ,
b100000 C
1'
#230000
0'
#235000
1!
0/
b10011 5
b110 #
b110 0
b110 4
b0 9
b0 3
b0 .
b1000 2
b1000 7
b110 6
b110 8
b100000000000001100010011 &
b100000000000001100010011 )
b11100 %
b11100 ,
b11100 C
1'
#240000
0'
#245000
0!
1/
b1100011 5
b11101 #
b11101 0
b11101 4
b1 9
b101 3
b1000 .
b110 2
b11111111111111111111111111100110 7
b11111111111111111111111111111101 6
b11111111111111111111111111111100 8
b11111110011000101001111011100011 &
b11111110011000101001111011100011 )
b1000 M
b100000 %
b100000 ,
b100000 C
1'
#250000
0'
#255000
1!
0/
b10011 5
b110 #
b110 0
b110 4
b0 9
b0 3
b0 .
b1000 2
b1000 7
b110 6
b110 8
b100000000000001100010011 &
b100000000000001100010011 )
b11100 %
b11100 ,
b11100 C
1'
#260000
0'
#265000
0!
1/
b1100011 5
b11101 #
b11101 0
b11101 4
b1 9
b101 3
b1000 .
b110 2
b11111111111111111111111111100110 7
b11111111111111111111111111111101 6
b11111111111111111111111111111100 8
b11111110011000101001111011100011 &
b11111110011000101001111011100011 )
b1000 M
b100000 %
b100000 ,
b100000 C
1'
#270000
0'
#275000
1!
0/
b10011 5
b110 #
b110 0
b110 4
b0 9
b0 3
b0 .
b1000 2
b1000 7
b110 6
b110 8
b100000000000001100010011 &
b100000000000001100010011 )
b11100 %
b11100 ,
b11100 C
1'
#280000
0'
#285000
0!
1/
b1100011 5
b11101 #
b11101 0
b11101 4
b1 9
b101 3
b1000 .
b110 2
b11111111111111111111111111100110 7
b11111111111111111111111111111101 6
b11111111111111111111111111111100 8
b11111110011000101001111011100011 &
b11111110011000101001111011100011 )
b1000 M
b100000 %
b100000 ,
b100000 C
1'
#290000
0'
#295000
1!
0/
b10011 5
b110 #
b110 0
b110 4
b0 9
b0 3
b0 .
b1000 2
b1000 7
b110 6
b110 8
b100000000000001100010011 &
b100000000000001100010011 )
b11100 %
b11100 ,
b11100 C
1'
#300000
0'
#305000
0!
1/
b1100011 5
b11101 #
b11101 0
b11101 4
b1 9
b101 3
b1000 .
b110 2
b11111111111111111111111111100110 7
b11111111111111111111111111111101 6
b11111111111111111111111111111100 8
b11111110011000101001111011100011 &
b11111110011000101001111011100011 )
b1000 M
b100000 %
b100000 ,
b100000 C
1'
#310000
0'
#315000
1!
0/
b10011 5
b110 #
b110 0
b110 4
b0 9
b0 3
b0 .
b1000 2
b1000 7
b110 6
b110 8
b100000000000001100010011 &
b100000000000001100010011 )
b11100 %
b11100 ,
b11100 C
1'
#320000
0'
#325000
0!
1/
b1100011 5
b11101 #
b11101 0
b11101 4
b1 9
b101 3
b1000 .
b110 2
b11111111111111111111111111100110 7
b11111111111111111111111111111101 6
b11111111111111111111111111111100 8
b11111110011000101001111011100011 &
b11111110011000101001111011100011 )
b1000 M
b100000 %
b100000 ,
b100000 C
1'
#330000
0'
#335000
1!
0/
b10011 5
b110 #
b110 0
b110 4
b0 9
b0 3
b0 .
b1000 2
b1000 7
b110 6
b110 8
b100000000000001100010011 &
b100000000000001100010011 )
b11100 %
b11100 ,
b11100 C
1'
#340000
0'
#345000
0!
1/
b1100011 5
b11101 #
b11101 0
b11101 4
b1 9
b101 3
b1000 .
b110 2
b11111111111111111111111111100110 7
b11111111111111111111111111111101 6
b11111111111111111111111111111100 8
b11111110011000101001111011100011 &
b11111110011000101001111011100011 )
b1000 M
b100000 %
b100000 ,
b100000 C
1'
#350000
0'
#355000
1!
0/
b10011 5
b110 #
b110 0
b110 4
b0 9
b0 3
b0 .
b1000 2
b1000 7
b110 6
b110 8
b100000000000001100010011 &
b100000000000001100010011 )
b11100 %
b11100 ,
b11100 C
1'
#360000
0'
#365000
0!
1/
b1100011 5
b11101 #
b11101 0
b11101 4
b1 9
b101 3
b1000 .
b110 2
b11111111111111111111111111100110 7
b11111111111111111111111111111101 6
b11111111111111111111111111111100 8
b11111110011000101001111011100011 &
b11111110011000101001111011100011 )
b1000 M
b100000 %
b100000 ,
b100000 C
1'
#370000
0'
#375000
1!
0/
b10011 5
b110 #
b110 0
b110 4
b0 9
b0 3
b0 .
b1000 2
b1000 7
b110 6
b110 8
b100000000000001100010011 &
b100000000000001100010011 )
b11100 %
b11100 ,
b11100 C
1'
#380000
0'
#385000
0!
1/
b1100011 5
b11101 #
b11101 0
b11101 4
b1 9
b101 3
b1000 .
b110 2
b11111111111111111111111111100110 7
b11111111111111111111111111111101 6
b11111111111111111111111111111100 8
b11111110011000101001111011100011 &
b11111110011000101001111011100011 )
b1000 M
b100000 %
b100000 ,
b100000 C
1'
#390000
0'
#395000
1!
0/
b10011 5
b110 #
b110 0
b110 4
b0 9
b0 3
b0 .
b1000 2
b1000 7
b110 6
b110 8
b100000000000001100010011 &
b100000000000001100010011 )
b11100 %
b11100 ,
b11100 C
1'
#400000
0'
#405000
0!
1/
b1100011 5
b11101 #
b11101 0
b11101 4
b1 9
b101 3
b1000 .
b110 2
b11111111111111111111111111100110 7
b11111111111111111111111111111101 6
b11111111111111111111111111111100 8
b11111110011000101001111011100011 &
b11111110011000101001111011100011 )
b1000 M
b100000 %
b100000 ,
b100000 C
1'
