designs/fsm/fsm_dut.sv
`timescale 1ns / 1ps

// One deliberate flaw per §8.8 check, the way designs/checks does it for §8.11.
//
// Every flaw here is found **without a trace**. That is the whole claim of §8.8:
// "un FSM cu o stare moarta e un bug garantat pe care nicio simulare nu-l
// gaseste daca stimulii n-au ajuns acolo". The testbench beside this file
// deliberately never drives the machine into most of them, so a run that passes
// is not evidence of anything — and the checks still report all five.
//
//   1. dead state          `bad_dead.state`, S_TRAP: enter and never leave
//   2. unreachable state   `bad_unreach.state`, S_ORPHAN: nothing goes there
//   3. impossible guard    `bad_typo.state`, a condition that contradicts itself
//   4. incomplete guards   `bad_partial.state`, S_WAIT: one exit, no else
//   5. incomplete reset    `bad_reset.state`, the companion counter never resets
//
// `good.state` is the control: a clean four-state machine that must produce no
// findings at all. A check that fires on it is a false positive, and a false
// positive is what gets a static check switched off.

// --- the control: nothing should be reported here ---------------------------
module fsm_good (
    input  logic clk,
    input  logic rst_n,
    input  logic go,
    input  logic ack,
    output logic busy
);
    localparam logic [1:0] S_IDLE = 2'd0, S_RUN = 2'd1, S_DONE = 2'd2;
    logic [1:0] state;
    logic [3:0] count;

    assign busy = (state != S_IDLE);

    always_ff @(posedge clk or negedge rst_n) begin
        if (!rst_n) begin
            state <= S_IDLE;
            count <= 4'd0;
        end else begin
            case (state)
                S_IDLE:  state <= go  ? S_RUN  : S_IDLE;
                S_RUN:   begin state <= ack ? S_DONE : S_RUN; count <= count + 4'd1; end
                S_DONE:  state <= S_IDLE;
                default: state <= S_IDLE;
            endcase
        end
    end
endmodule

// --- 1. dead state ----------------------------------------------------------
module fsm_dead (
    input  logic clk,
    input  logic rst_n,
    input  logic err,
    output logic trapped
);
    localparam logic [1:0] S_IDLE = 2'd0, S_WORK = 2'd1, S_TRAP = 2'd2;
    logic [1:0] state;

    assign trapped = (state == S_TRAP);

    always_ff @(posedge clk or negedge rst_n) begin
        if (!rst_n) state <= S_IDLE;
        else begin
            case (state)
                S_IDLE:  state <= S_WORK;
                S_WORK:  state <= err ? S_TRAP : S_IDLE;
                // THE BUG: S_TRAP has no way out. Entering it stops the machine
                // until the chip is reset. Nothing here is wrong syntactically
                // and no simulation finds it unless `err` happens to go high.
                S_TRAP:  state <= S_TRAP;
                default: state <= S_IDLE;
            endcase
        end
    end
endmodule

// --- 2. unreachable state ---------------------------------------------------
module fsm_unreachable (
    input  logic clk,
    input  logic rst_n,
    input  logic go,
    output logic active
);
    localparam logic [1:0] S_IDLE = 2'd0, S_RUN = 2'd1, S_ORPHAN = 2'd2;
    logic [1:0] state;

    assign active = (state == S_RUN) || (state == S_ORPHAN);

    always_ff @(posedge clk or negedge rst_n) begin
        if (!rst_n) state <= S_IDLE;
        else begin
            case (state)
                S_IDLE:   state <= go ? S_RUN : S_IDLE;
                S_RUN:    state <= S_IDLE;
                // THE BUG: S_ORPHAN is written and reasoned about, but no
                // transition ever enters it. Either dead code, or the edge into
                // it was forgotten.
                S_ORPHAN: state <= S_IDLE;
                default:  state <= S_IDLE;
            endcase
        end
    end
endmodule

// --- 3. impossible transition ----------------------------------------------
module fsm_typo (
    input  logic clk,
    input  logic rst_n,
    input  logic ready,
    output logic done
);
    localparam logic [1:0] S_IDLE = 2'd0, S_SEND = 2'd1, S_WAIT = 2'd2;
    logic [1:0] state;

    assign done = (state == S_IDLE);

    always_ff @(posedge clk or negedge rst_n) begin
        if (!rst_n) state <= S_IDLE;
        else begin
            case (state)
                S_IDLE: state <= ready ? S_SEND : S_IDLE;
                S_SEND: state <= S_WAIT;
                S_WAIT: begin
                    // THE BUG: a mistyped condition. `ready && !ready` is never
                    // true, so the machine can never leave S_WAIT this way —
                    // the branch is dead and the state is stuck with it.
                    if (ready && !ready) state <= S_IDLE;
                    else                 state <= S_WAIT;
                end
                default: state <= S_IDLE;
            endcase
        end
    end
endmodule

// --- 4. incomplete guards ---------------------------------------------------
module fsm_partial (
    input  logic clk,
    input  logic rst_n,
    input  logic start,
    input  logic grant,
    output logic waiting
);
    localparam logic [1:0] S_IDLE = 2'd0, S_WAIT = 2'd1, S_GO = 2'd2;
    logic [1:0] state;

    assign waiting = (state == S_WAIT);

    always_ff @(posedge clk or negedge rst_n) begin
        if (!rst_n) state <= S_IDLE;
        else begin
            case (state)
                S_IDLE: state <= start ? S_WAIT : S_IDLE;
                // THE BUG (a mild one, reported at info): only the happy path is
                // written. With no `else` and no self-transition, an unexpected
                // input leaves the machine where it is — intended for a state
                // that waits, a hang for one that should not.
                S_WAIT: if (grant) state <= S_GO;
                S_GO:   state <= S_IDLE;
                default: state <= S_IDLE;
            endcase
        end
    end
endmodule

// --- 5. incomplete reset ----------------------------------------------------
module fsm_unreset (
    input  logic clk,
    input  logic rst_n,
    input  logic tick,
    output logic [3:0] ticks
);
    localparam logic S_IDLE = 1'b0, S_COUNT = 1'b1;
    logic       state;
    logic [3:0] count;

    assign ticks = count;

    always_ff @(posedge clk or negedge rst_n) begin
        if (!rst_n) begin
            state <= S_IDLE;
            // THE BUG: `count` is written in this block beside the state and is
            // *not* reset. On the board it starts at whatever the flops power up
            // to, so the machine's first pass is non-deterministic — and the
            // simulator hides it, because the testbench initialises memory.
        end else begin
            case (state)
                S_IDLE:  state <= tick ? S_COUNT : S_IDLE;
                S_COUNT: begin state <= S_IDLE; count <= count + 4'd1; end
                default: state <= S_IDLE;
            endcase
        end
    end
endmodule

designs/fsm/tb_fsm.sv
`timescale 1ns / 1ps

// Drives the six machines of `fsm_dut.sv` gently, and that is the point.
//
// §8.8's claim is that the static checks find what a simulation cannot: the
// stimulus below deliberately never asserts `err`, never asserts `grant`, and
// never reaches the second half of any machine. The run passes, the waveform
// looks healthy — and `veritrace check --rtl designs/fsm` still reports all
// five injected flaws, because it reads the RTL rather than the run.
//
// The dump exists so the §8.8 step 5 overlay has something to colour, and so
// the reference designs stay uniform. No check here depends on it.
module tb_fsm;
    logic clk = 1'b0;
    logic rst_n = 1'b0;
    always #5 clk = ~clk;

    logic go = 1'b0, ack = 1'b0, ready = 1'b0, start = 1'b0, tick = 1'b0;
    // Never asserted: the states they would reach are the ones the checks find
    // without ever going there.
    logic err = 1'b0, grant = 1'b0;

    logic busy, trapped, active, done, waiting;
    logic [3:0] ticks;

    fsm_good        good       (.clk, .rst_n, .go, .ack, .busy);
    fsm_dead        bad_dead   (.clk, .rst_n, .err, .trapped);
    fsm_unreachable bad_unreach(.clk, .rst_n, .go, .active);
    fsm_typo        bad_typo   (.clk, .rst_n, .ready, .done);
    fsm_partial     bad_partial(.clk, .rst_n, .start, .grant, .waiting);
    fsm_unreset     bad_reset  (.clk, .rst_n, .tick, .ticks);

    initial begin
        $dumpfile("dump.vcd");
        $dumpvars(0, tb_fsm);

        repeat (3) @(posedge clk);
        rst_n <= 1'b1;

        repeat (2) @(posedge clk);
        go    <= 1'b1;
        ready <= 1'b1;
        start <= 1'b1;
        tick  <= 1'b1;

        repeat (4) @(posedge clk);
        ack <= 1'b1;

        repeat (30) @(posedge clk);
        $display("tb_fsm: done, no assertion fired");
        $finish;
    end
endmodule

designs/fsm/dump.vcd
$date
	Thu Aug 13 20:38:48 2026
$end
$version
	Icarus Verilog
$end
$timescale
	1ps
$end
$scope module tb_fsm $end
$var wire 1 ! waiting $end
$var wire 1 " trapped $end
$var wire 4 # ticks [3:0] $end
$var wire 1 $ done $end
$var wire 1 % busy $end
$var wire 1 & active $end
$var reg 1 ' ack $end
$var reg 1 ( clk $end
$var reg 1 ) err $end
$var reg 1 * go $end
$var reg 1 + grant $end
$var reg 1 , ready $end
$var reg 1 - rst_n $end
$var reg 1 . start $end
$var reg 1 / tick $end
$scope module bad_dead $end
$var wire 1 ( clk $end
$var wire 1 ) err $end
$var wire 1 - rst_n $end
$var wire 1 " trapped $end
$var parameter 2 0 S_IDLE $end
$var parameter 2 1 S_TRAP $end
$var parameter 2 2 S_WORK $end
$var reg 2 3 state [1:0] $end
$upscope $end
$scope module bad_partial $end
$var wire 1 ( clk $end
$var wire 1 + grant $end
$var wire 1 - rst_n $end
$var wire 1 . start $end
$var wire 1 ! waiting $end
$var parameter 2 4 S_GO $end
$var parameter 2 5 S_IDLE $end
$var parameter 2 6 S_WAIT $end
$var reg 2 7 state [1:0] $end
$upscope $end
$scope module bad_reset $end
$var wire 1 ( clk $end
$var wire 1 - rst_n $end
$var wire 1 / tick $end
$var wire 4 8 ticks [3:0] $end
$var parameter 1 9 S_COUNT $end
$var parameter 1 : S_IDLE $end
$var reg 4 ; count [3:0] $end
$var reg 1 < state $end
$upscope $end
$scope module bad_typo $end
$var wire 1 ( clk $end
$var wire 1 , ready $end
$var wire 1 - rst_n $end
$var wire 1 $ done $end
$var parameter 2 = S_IDLE $end
$var parameter 2 > S_SEND $end
$var parameter 2 ? S_WAIT $end
$var reg 2 @ state [1:0] $end
$upscope $end
$scope module bad_unreach $end
$var wire 1 & active $end
$var wire 1 ( clk $end
$var wire 1 * go $end
$var wire 1 - rst_n $end
$var parameter 2 A S_IDLE $end
$var parameter 2 B S_ORPHAN $end
$var parameter 2 C S_RUN $end
$var reg 2 D state [1:0] $end
$upscope $end
$scope module good $end
$var wire 1 ' ack $end
$var wire 1 ( clk $end
$var wire 1 * go $end
$var wire 1 - rst_n $end
$var wire 1 % busy $end
$var parameter 2 E S_DONE $end
$var parameter 2 F S_IDLE $end
$var parameter 2 G S_RUN $end
$var reg 4 H count [3:0] $end
$var reg 2 I state [1:0] $end
$upscope $end
$upscope $end
$enddefinitions $end
$comment Show the parameter values. $end
$dumpall
b1 G
b0 F
b10 E
b1 C
b10 B
b0 A
b10 ?
b1 >
b0 =
0:
19
b1 6
b0 5
b10 4
b1 2
b10 1
b0 0
$end
#0
$dumpvars
bx I
bx H
bx D
bx @
x<
bx ;
bx 8
bx 7
bx 3
0/
0.
0-
0,
0+
0*
0)
0(
0'
x&
x%
x$
bx #
x"
x!
$end
#5000
0&
b0 H
0%
b0 I
0"
b0 3
b0 D
1$
b0 @
0!
b0 7
0<
1(
#10000
0(
#15000
1(
#20000
0(
#25000
1-
1(
#30000
0(
#35000
b1 3
1(
#40000
0(
#45000
b0 3
1/
1.
1,
1*
1(
#50000
0(
#55000
1&
1<
1!
b1 7
0$
b1 @
b1 D
b1 3
1%
b1 I
1(
#60000
0(
#65000
0&
b1 H
b0 3
b0 D
b10 @
0<
1(
#70000
0(
#75000
1&
1<
b1 D
b1 3
b10 H
1(
#80000
0(
#85000
0&
b11 H
b0 3
b0 D
0<
1'
1(
#90000
0(
#95000
1&
1<
b1 D
b1 3
b100 H
b10 I
1(
#100000
0(
#105000
0&
0%
b0 I
b0 3
b0 D
0<
1(
#110000
0(
#115000
1&
1<
b1 D
b1 3
1%
b1 I
1(
#120000
0(
#125000
0&
b101 H
b10 I
b0 3
b0 D
0<
1(
#130000
0(
#135000
1&
1<
b1 D
b1 3
0%
b0 I
1(
#140000
0(
#145000
0&
1%
b1 I
b0 3
b0 D
0<
1(
#150000
0(
#155000
1&
1<
b1 D
b1 3
b110 H
b10 I
1(
#160000
0(
#165000
0&
0%
b0 I
b0 3
b0 D
0<
1(
#170000
0(
#175000
1&
1<
b1 D
b1 3
1%
b1 I
1(
#180000
0(
#185000
0&
b111 H
b10 I
b0 3
b0 D
0<
1(
#190000
0(
#195000
1&
1<
b1 D
b1 3
0%
b0 I
1(
#200000
0(
#205000
0&
1%
b1 I
b0 3
b0 D
0<
1(
#210000
0(
#215000
1&
1<
b1 D
b1 3
b1000 H
b10 I
1(
#220000
0(
#225000
0&
0%
b0 I
b0 3
b0 D
0<
1(
#230000
0(
#235000
1&
1<
b1 D
b1 3
1%
b1 I
1(
#240000
0(
#245000
0&
b1001 H
b10 I
b0 3
b0 D
0<
1(
#250000
0(
#255000
1&
1<
b1 D
b1 3
0%
b0 I
1(
#260000
0(
#265000
0&
1%
b1 I
b0 3
b0 D
0<
1(
#270000
0(
#275000
1&
1<
b1 D
b1 3
b1010 H
b10 I
1(
#280000
0(
#285000
0&
0%
b0 I
b0 3
b0 D
0<
1(
#290000
0(
#295000
1&
1<
b1 D
b1 3
1%
b1 I
1(
#300000
0(
#305000
0&
b1011 H
b10 I
b0 3
b0 D
0<
1(
#310000
0(
#315000
1&
1<
b1 D
b1 3
0%
b0 I
1(
#320000
0(
#325000
0&
1%
b1 I
b0 3
b0 D
0<
1(
#330000
0(
#335000
1&
1<
b1 D
b1 3
b1100 H
b10 I
1(
#340000
0(
#345000
0&
0%
b0 I
b0 3
b0 D
0<
1(
#350000
0(
#355000
1&
1<
b1 D
b1 3
1%
b1 I
1(
#360000
0(
#365000
0&
b1101 H
b10 I
b0 3
b0 D
0<
1(
#370000
0(
#375000
1&
1<
b1 D
b1 3
0%
b0 I
1(
#380000
0(
#385000
0&
1%
b1 I
b0 3
b0 D
0<
1(
