designs/fifo_async_cdc/fifo_async.sv
`timescale 1ns / 1ps

// §14.1 reference bug: a Gray write pointer crosses directly into the read
// clock domain through only one flop.  The first stage is also not reset, so
// the consumer observes X before its first sample.  A correct async FIFO uses
// two destination-domain synchroniser flops before comparing pointers.
module fifo_async (
    input  logic wr_clk,
    input  logic rd_clk,
    input  logic rst_n,
    input  logic wr_en,
    output logic empty,
    output logic [3:0] wr_gray_seen
);
    logic [3:0] wr_bin;
    logic [3:0] wr_gray;
    logic [3:0] rd_gray;

    assign wr_gray = (wr_bin >> 1) ^ wr_bin;
    assign empty = (wr_gray_seen == rd_gray);

    always_ff @(posedge wr_clk or negedge rst_n) begin
        if (!rst_n) wr_bin <= '0;
        else if (wr_en) wr_bin <= wr_bin + 1'b1;
    end

    always_ff @(posedge rd_clk or negedge rst_n) begin
        if (!rst_n) rd_gray <= '0;
        else rd_gray <= rd_gray;
    end

    // BUG: one unreset capture stage, used directly by read-domain logic.
    always_ff @(posedge rd_clk) begin
        wr_gray_seen <= wr_gray;
    end
endmodule

designs/fifo_async_cdc/tb_fifo_async.sv
`timescale 1ns / 1ps

module tb_fifo_async;
    logic wr_clk = 1'b0;
    logic rd_clk = 1'b0;
    logic rst_n = 1'b0;
    logic wr_en = 1'b0;
    logic empty;
    logic [3:0] wr_gray_seen;

    always #4 wr_clk = ~wr_clk;
    always #5 rd_clk = ~rd_clk;
    fifo_async dut (.*);

    initial begin
        $dumpfile("dump.vcd");
        $dumpvars(0, tb_fifo_async);
        #13 rst_n = 1'b1;
        #3 wr_en = 1'b1;
        repeat (8) @(posedge wr_clk);
        wr_en = 1'b0;
        repeat (8) @(posedge rd_clk);
        $finish;
    end
endmodule

designs/fifo_async_cdc/dump.vcd
$date
	Mon Aug 31 18:57:45 2026
$end
$version
	Icarus Verilog
$end
$timescale
	1ps
$end
$scope module tb_fifo_async $end
$var wire 4 ! wr_gray_seen [3:0] $end
$var wire 1 " empty $end
$var reg 1 # rd_clk $end
$var reg 1 $ rst_n $end
$var reg 1 % wr_clk $end
$var reg 1 & wr_en $end
$scope module dut $end
$var wire 1 # rd_clk $end
$var wire 1 $ rst_n $end
$var wire 1 % wr_clk $end
$var wire 1 & wr_en $end
$var wire 4 ' wr_gray [3:0] $end
$var wire 1 " empty $end
$var reg 4 ( rd_gray [3:0] $end
$var reg 4 ) wr_bin [3:0] $end
$var reg 4 * wr_gray_seen [3:0] $end
$upscope $end
$upscope $end
$enddefinitions $end
$comment Show the parameter values. $end
$dumpall
$end
#0
$dumpvars
bx *
bx )
bx (
bx '
0&
0%
0$
0#
x"
bx !
$end
#4000
b0 '
b0 )
1%
#5000
1"
b0 !
b0 *
b0 (
1#
#8000
0%
#10000
0#
#12000
1%
#13000
1$
#15000
1#
#16000
1&
0%
#20000
b1 '
b1 )
1%
0#
#24000
0%
#25000
0"
b1 !
b1 *
1#
#28000
b11 '
b10 )
1%
#30000
0#
#32000
0%
#35000
b11 !
b11 *
1#
#36000
b10 '
b11 )
1%
#40000
0%
0#
#44000
b110 '
b100 )
1%
#45000
b110 !
b110 *
1#
#48000
0%
#50000
0#
#52000
b111 '
b101 )
1%
#55000
b111 !
b111 *
1#
#56000
0%
#60000
b101 '
b110 )
1%
0#
#64000
0%
#65000
b101 !
b101 *
1#
#68000
b100 '
b111 )
1%
#70000
0#
#72000
0%
#75000
b100 !
b100 *
1#
#76000
0&
1%
