designs/lanes/lanes.sv
// Correlation stress design: the two shapes that break naive name matching
// (§7.1) — a for-generate block and an instance array. Both produce indexed
// hierarchy in the trace (`g_lane[2].u_fifo.wr_ptr`, `u_cnt[1].q`) that only
// exists after elaboration.
`timescale 1ns / 1ps

module lane_fifo #(
    parameter int WIDTH = 8,
    parameter int DEPTH = 4
) (
    input  logic             clk,
    input  logic             rst_n,
    input  logic             push,
    input  logic [WIDTH-1:0] din,
    output logic [WIDTH-1:0] dout,
    output logic             full
);
    localparam int AW = $clog2(DEPTH);
    logic [WIDTH-1:0] mem [DEPTH];
    logic [AW:0]      wr_ptr;

    assign full = wr_ptr[AW];
    assign dout = mem[wr_ptr[AW-1:0]];

    always_ff @(posedge clk or negedge rst_n) begin
        if (!rst_n) wr_ptr <= '0;
        else if (push && !full) begin
            mem[wr_ptr[AW-1:0]] <= din;
            wr_ptr <= wr_ptr + 1'b1;
        end
    end
endmodule

// Instantiated as an array below, to exercise the `u_cnt[1].q` form.
module counter #(
    parameter int W = 4
) (
    input  logic         clk,
    input  logic         rst_n,
    input  logic         en,
    output logic [W-1:0] q
);
    always_ff @(posedge clk or negedge rst_n) begin
        if (!rst_n)   q <= '0;
        else if (en)  q <= q + 1'b1;
    end
endmodule

module lanes #(
    parameter int NLANES = 4,
    parameter int WIDTH  = 8
) (
    input  logic                     clk,
    input  logic                     rst_n,
    input  logic [NLANES-1:0]        push,
    input  logic [WIDTH-1:0]         din,
    output logic [NLANES-1:0]        full,
    output logic [WIDTH-1:0]         dout0,
    output logic [NLANES-1:0]        tick
);
    // for-generate: hierarchy becomes lanes.g_lane[i].u_fifo.*
    logic [WIDTH-1:0] lane_dout [NLANES];
    genvar i;
    generate
        for (i = 0; i < NLANES; i++) begin : g_lane
            logic busy;
            // 64 entries on purpose: deeper than Verilator's default
            // --trace-max-array of 32, so the memory only reaches the trace
            // when the mandatory flags of §4.0 are used.
            lane_fifo #(.WIDTH(WIDTH), .DEPTH(64)) u_fifo (
                .clk   (clk),
                .rst_n (rst_n),
                .push  (push[i]),
                .din   (din),
                .dout  (lane_dout[i]),
                .full  (full[i])
            );
            assign busy = full[i] & push[i];
        end
    endgenerate

    // Instance array: hierarchy becomes lanes.u_cnt[i].*. The output is one
    // packed vector, which the array splits 4 bits per instance — the idiom
    // instance arrays exist for, and the one simulators agree on.
    logic [NLANES*4-1:0] cnt_q;
    counter #(.W(4)) u_cnt [NLANES-1:0] (
        .clk   (clk),
        .rst_n (rst_n),
        .en    (push),
        .q     (cnt_q)
    );

    assign dout0 = lane_dout[0];
    generate
        for (i = 0; i < NLANES; i++) begin : g_tick
            assign tick[i] = (cnt_q[i*4 +: 4] == 4'hF);
        end
    endgenerate
endmodule

designs/lanes/tb_lanes.sv
`timescale 1ns / 1ps

module tb_lanes;
    localparam int NLANES = 4;
    localparam int WIDTH = 8;

    logic clk = 1'b0;
    logic rst_n;
    logic [NLANES-1:0] push;
    logic [WIDTH-1:0]  din;
    logic [NLANES-1:0] full, tick;
    logic [WIDTH-1:0]  dout0;

    lanes #(.NLANES(NLANES), .WIDTH(WIDTH)) dut (
        .clk(clk), .rst_n(rst_n), .push(push), .din(din),
        .full(full), .dout0(dout0), .tick(tick)
    );

    always #5 clk = ~clk;

    initial begin
        $dumpfile("dump.vcd");
        $dumpvars(0, tb_lanes);
        // Generate blocks and instance arrays put memories behind indexed
        // scopes; Icarus needs each element named explicitly.
        // Dumping unpacked-array elements needs an explicit element select,
        // which the LRM does not allow as a $dumpvars argument. Icarus accepts
        // it as an extension; slang and ModelSim reject it. Icarus predefines
        // __ICARUS__, so this stays an Icarus-only path and every other tool
        // reads the file cleanly.
`ifdef __ICARUS__
        $dumpvars(1, dut.g_lane[0].u_fifo.mem[0], dut.g_lane[1].u_fifo.mem[0]);
`endif
    end

    initial begin
        rst_n = 1'b0;
        push  = '0;
        din   = 8'h00;
        repeat (2) @(posedge clk);
        rst_n = 1'b1;

        for (int i = 0; i < 24; i++) begin
            @(negedge clk);
            push = NLANES'(i);
            din  = 8'h10 + i[7:0];
        end

        @(negedge clk);
        push = '1;
        repeat (20) @(negedge clk);
        push = '0;

        repeat (4) @(posedge clk);
        $finish;
    end
endmodule

designs/lanes/verilator_with.vcd
$version Generated by VerilatedVcd $end
$timescale 1ps $end
 $scope module $rootio $end
 $upscope $end
 $scope module tb_lanes $end
  $var wire 32 M# NLANES [31:0] $end
  $var wire 32 N# WIDTH [31:0] $end
  $var wire 1 # clk $end
  $var wire 1 $ rst_n $end
  $var wire 4 % push [3:0] $end
  $var wire 8 & din [7:0] $end
  $var wire 4 ' full [3:0] $end
  $var wire 4 ( tick [3:0] $end
  $var wire 8 ) dout0 [7:0] $end
  $scope module dut $end
   $var wire 32 M# NLANES [31:0] $end
   $var wire 32 N# WIDTH [31:0] $end
   $var wire 1 + clk $end
   $var wire 1 , rst_n $end
   $var wire 4 - push [3:0] $end
   $var wire 8 . din [7:0] $end
   $var wire 4 / full [3:0] $end
   $var wire 8 0 dout0 [7:0] $end
   $var wire 4 1 tick [3:0] $end
   $var wire 8 2 lane_dout[0] [7:0] $end
   $var wire 8 3 lane_dout[1] [7:0] $end
   $var wire 8 4 lane_dout[2] [7:0] $end
   $var wire 8 5 lane_dout[3] [7:0] $end
   $var wire 16 6 cnt_q [15:0] $end
   $scope module u_cnt[0] $end
    $var wire 32 M# W [31:0] $end
    $var wire 1 G clk $end
    $var wire 1 H rst_n $end
    $var wire 1 I en $end
    $var wire 4 J q [3:0] $end
   $upscope $end
   $scope module u_cnt[1] $end
    $var wire 32 M# W [31:0] $end
    $var wire 1 C clk $end
    $var wire 1 D rst_n $end
    $var wire 1 E en $end
    $var wire 4 F q [3:0] $end
   $upscope $end
   $scope module u_cnt[2] $end
    $var wire 32 M# W [31:0] $end
    $var wire 1 ? clk $end
    $var wire 1 @ rst_n $end
    $var wire 1 A en $end
    $var wire 4 B q [3:0] $end
   $upscope $end
   $scope module u_cnt[3] $end
    $var wire 32 M# W [31:0] $end
    $var wire 1 ; clk $end
    $var wire 1 < rst_n $end
    $var wire 1 = en $end
    $var wire 4 > q [3:0] $end
   $upscope $end
   $scope module g_lane[0] $end
    $var wire 1 7 busy $end
    $scope module u_fifo $end
     $var wire 32 N# WIDTH [31:0] $end
     $var wire 32 O# DEPTH [31:0] $end
     $var wire 1 K clk $end
     $var wire 1 L rst_n $end
     $var wire 1 M push $end
     $var wire 8 N din [7:0] $end
     $var wire 8 O dout [7:0] $end
     $var wire 1 P full $end
     $var wire 32 P# AW [31:0] $end
     $var wire 8 Q mem[0] [7:0] $end
     $var wire 8 R mem[1] [7:0] $end
     $var wire 8 S mem[2] [7:0] $end
     $var wire 8 T mem[3] [7:0] $end
     $var wire 8 U mem[4] [7:0] $end
     $var wire 8 V mem[5] [7:0] $end
     $var wire 8 W mem[6] [7:0] $end
     $var wire 8 X mem[7] [7:0] $end
     $var wire 8 Y mem[8] [7:0] $end
     $var wire 8 Z mem[9] [7:0] $end
     $var wire 8 [ mem[10] [7:0] $end
     $var wire 8 \ mem[11] [7:0] $end
     $var wire 8 ] mem[12] [7:0] $end
     $var wire 8 ^ mem[13] [7:0] $end
     $var wire 8 _ mem[14] [7:0] $end
     $var wire 8 ` mem[15] [7:0] $end
     $var wire 8 a mem[16] [7:0] $end
     $var wire 8 b mem[17] [7:0] $end
     $var wire 8 c mem[18] [7:0] $end
     $var wire 8 d mem[19] [7:0] $end
     $var wire 8 e mem[20] [7:0] $end
     $var wire 8 f mem[21] [7:0] $end
     $var wire 8 g mem[22] [7:0] $end
     $var wire 8 h mem[23] [7:0] $end
     $var wire 8 i mem[24] [7:0] $end
     $var wire 8 j mem[25] [7:0] $end
     $var wire 8 k mem[26] [7:0] $end
     $var wire 8 l mem[27] [7:0] $end
     $var wire 8 m mem[28] [7:0] $end
     $var wire 8 n mem[29] [7:0] $end
     $var wire 8 o mem[30] [7:0] $end
     $var wire 8 p mem[31] [7:0] $end
     $var wire 8 q mem[32] [7:0] $end
     $var wire 8 r mem[33] [7:0] $end
     $var wire 8 s mem[34] [7:0] $end
     $var wire 8 t mem[35] [7:0] $end
     $var wire 8 u mem[36] [7:0] $end
     $var wire 8 v mem[37] [7:0] $end
     $var wire 8 w mem[38] [7:0] $end
     $var wire 8 x mem[39] [7:0] $end
     $var wire 8 y mem[40] [7:0] $end
     $var wire 8 z mem[41] [7:0] $end
     $var wire 8 { mem[42] [7:0] $end
     $var wire 8 | mem[43] [7:0] $end
     $var wire 8 } mem[44] [7:0] $end
     $var wire 8 ~ mem[45] [7:0] $end
     $var wire 8 !! mem[46] [7:0] $end
     $var wire 8 "! mem[47] [7:0] $end
     $var wire 8 #! mem[48] [7:0] $end
     $var wire 8 $! mem[49] [7:0] $end
     $var wire 8 %! mem[50] [7:0] $end
     $var wire 8 &! mem[51] [7:0] $end
     $var wire 8 '! mem[52] [7:0] $end
     $var wire 8 (! mem[53] [7:0] $end
     $var wire 8 )! mem[54] [7:0] $end
     $var wire 8 *! mem[55] [7:0] $end
     $var wire 8 +! mem[56] [7:0] $end
     $var wire 8 ,! mem[57] [7:0] $end
     $var wire 8 -! mem[58] [7:0] $end
     $var wire 8 .! mem[59] [7:0] $end
     $var wire 8 /! mem[60] [7:0] $end
     $var wire 8 0! mem[61] [7:0] $end
     $var wire 8 1! mem[62] [7:0] $end
     $var wire 8 2! mem[63] [7:0] $end
     $var wire 7 3! wr_ptr [6:0] $end
    $upscope $end
   $upscope $end
   $scope module g_lane[1] $end
    $var wire 1 8 busy $end
    $scope module u_fifo $end
     $var wire 32 N# WIDTH [31:0] $end
     $var wire 32 O# DEPTH [31:0] $end
     $var wire 1 4! clk $end
     $var wire 1 5! rst_n $end
     $var wire 1 6! push $end
     $var wire 8 7! din [7:0] $end
     $var wire 8 8! dout [7:0] $end
     $var wire 1 9! full $end
     $var wire 32 P# AW [31:0] $end
     $var wire 8 :! mem[0] [7:0] $end
     $var wire 8 ;! mem[1] [7:0] $end
     $var wire 8 <! mem[2] [7:0] $end
     $var wire 8 =! mem[3] [7:0] $end
     $var wire 8 >! mem[4] [7:0] $end
     $var wire 8 ?! mem[5] [7:0] $end
     $var wire 8 @! mem[6] [7:0] $end
     $var wire 8 A! mem[7] [7:0] $end
     $var wire 8 B! mem[8] [7:0] $end
     $var wire 8 C! mem[9] [7:0] $end
     $var wire 8 D! mem[10] [7:0] $end
     $var wire 8 E! mem[11] [7:0] $end
     $var wire 8 F! mem[12] [7:0] $end
     $var wire 8 G! mem[13] [7:0] $end
     $var wire 8 H! mem[14] [7:0] $end
     $var wire 8 I! mem[15] [7:0] $end
     $var wire 8 J! mem[16] [7:0] $end
     $var wire 8 K! mem[17] [7:0] $end
     $var wire 8 L! mem[18] [7:0] $end
     $var wire 8 M! mem[19] [7:0] $end
     $var wire 8 N! mem[20] [7:0] $end
     $var wire 8 O! mem[21] [7:0] $end
     $var wire 8 P! mem[22] [7:0] $end
     $var wire 8 Q! mem[23] [7:0] $end
     $var wire 8 R! mem[24] [7:0] $end
     $var wire 8 S! mem[25] [7:0] $end
     $var wire 8 T! mem[26] [7:0] $end
     $var wire 8 U! mem[27] [7:0] $end
     $var wire 8 V! mem[28] [7:0] $end
     $var wire 8 W! mem[29] [7:0] $end
     $var wire 8 X! mem[30] [7:0] $end
     $var wire 8 Y! mem[31] [7:0] $end
     $var wire 8 Z! mem[32] [7:0] $end
     $var wire 8 [! mem[33] [7:0] $end
     $var wire 8 \! mem[34] [7:0] $end
     $var wire 8 ]! mem[35] [7:0] $end
     $var wire 8 ^! mem[36] [7:0] $end
     $var wire 8 _! mem[37] [7:0] $end
     $var wire 8 `! mem[38] [7:0] $end
     $var wire 8 a! mem[39] [7:0] $end
     $var wire 8 b! mem[40] [7:0] $end
     $var wire 8 c! mem[41] [7:0] $end
     $var wire 8 d! mem[42] [7:0] $end
     $var wire 8 e! mem[43] [7:0] $end
     $var wire 8 f! mem[44] [7:0] $end
     $var wire 8 g! mem[45] [7:0] $end
     $var wire 8 h! mem[46] [7:0] $end
     $var wire 8 i! mem[47] [7:0] $end
     $var wire 8 j! mem[48] [7:0] $end
     $var wire 8 k! mem[49] [7:0] $end
     $var wire 8 l! mem[50] [7:0] $end
     $var wire 8 m! mem[51] [7:0] $end
     $var wire 8 n! mem[52] [7:0] $end
     $var wire 8 o! mem[53] [7:0] $end
     $var wire 8 p! mem[54] [7:0] $end
     $var wire 8 q! mem[55] [7:0] $end
     $var wire 8 r! mem[56] [7:0] $end
     $var wire 8 s! mem[57] [7:0] $end
     $var wire 8 t! mem[58] [7:0] $end
     $var wire 8 u! mem[59] [7:0] $end
     $var wire 8 v! mem[60] [7:0] $end
     $var wire 8 w! mem[61] [7:0] $end
     $var wire 8 x! mem[62] [7:0] $end
     $var wire 8 y! mem[63] [7:0] $end
     $var wire 7 z! wr_ptr [6:0] $end
    $upscope $end
   $upscope $end
   $scope module g_lane[2] $end
    $var wire 1 9 busy $end
    $scope module u_fifo $end
     $var wire 32 N# WIDTH [31:0] $end
     $var wire 32 O# DEPTH [31:0] $end
     $var wire 1 {! clk $end
     $var wire 1 |! rst_n $end
     $var wire 1 }! push $end
     $var wire 8 ~! din [7:0] $end
     $var wire 8 !" dout [7:0] $end
     $var wire 1 "" full $end
     $var wire 32 P# AW [31:0] $end
     $var wire 8 #" mem[0] [7:0] $end
     $var wire 8 $" mem[1] [7:0] $end
     $var wire 8 %" mem[2] [7:0] $end
     $var wire 8 &" mem[3] [7:0] $end
     $var wire 8 '" mem[4] [7:0] $end
     $var wire 8 (" mem[5] [7:0] $end
     $var wire 8 )" mem[6] [7:0] $end
     $var wire 8 *" mem[7] [7:0] $end
     $var wire 8 +" mem[8] [7:0] $end
     $var wire 8 ," mem[9] [7:0] $end
     $var wire 8 -" mem[10] [7:0] $end
     $var wire 8 ." mem[11] [7:0] $end
     $var wire 8 /" mem[12] [7:0] $end
     $var wire 8 0" mem[13] [7:0] $end
     $var wire 8 1" mem[14] [7:0] $end
     $var wire 8 2" mem[15] [7:0] $end
     $var wire 8 3" mem[16] [7:0] $end
     $var wire 8 4" mem[17] [7:0] $end
     $var wire 8 5" mem[18] [7:0] $end
     $var wire 8 6" mem[19] [7:0] $end
     $var wire 8 7" mem[20] [7:0] $end
     $var wire 8 8" mem[21] [7:0] $end
     $var wire 8 9" mem[22] [7:0] $end
     $var wire 8 :" mem[23] [7:0] $end
     $var wire 8 ;" mem[24] [7:0] $end
     $var wire 8 <" mem[25] [7:0] $end
     $var wire 8 =" mem[26] [7:0] $end
     $var wire 8 >" mem[27] [7:0] $end
     $var wire 8 ?" mem[28] [7:0] $end
     $var wire 8 @" mem[29] [7:0] $end
     $var wire 8 A" mem[30] [7:0] $end
     $var wire 8 B" mem[31] [7:0] $end
     $var wire 8 C" mem[32] [7:0] $end
     $var wire 8 D" mem[33] [7:0] $end
     $var wire 8 E" mem[34] [7:0] $end
     $var wire 8 F" mem[35] [7:0] $end
     $var wire 8 G" mem[36] [7:0] $end
     $var wire 8 H" mem[37] [7:0] $end
     $var wire 8 I" mem[38] [7:0] $end
     $var wire 8 J" mem[39] [7:0] $end
     $var wire 8 K" mem[40] [7:0] $end
     $var wire 8 L" mem[41] [7:0] $end
     $var wire 8 M" mem[42] [7:0] $end
     $var wire 8 N" mem[43] [7:0] $end
     $var wire 8 O" mem[44] [7:0] $end
     $var wire 8 P" mem[45] [7:0] $end
     $var wire 8 Q" mem[46] [7:0] $end
     $var wire 8 R" mem[47] [7:0] $end
     $var wire 8 S" mem[48] [7:0] $end
     $var wire 8 T" mem[49] [7:0] $end
     $var wire 8 U" mem[50] [7:0] $end
     $var wire 8 V" mem[51] [7:0] $end
     $var wire 8 W" mem[52] [7:0] $end
     $var wire 8 X" mem[53] [7:0] $end
     $var wire 8 Y" mem[54] [7:0] $end
     $var wire 8 Z" mem[55] [7:0] $end
     $var wire 8 [" mem[56] [7:0] $end
     $var wire 8 \" mem[57] [7:0] $end
     $var wire 8 ]" mem[58] [7:0] $end
     $var wire 8 ^" mem[59] [7:0] $end
     $var wire 8 _" mem[60] [7:0] $end
     $var wire 8 `" mem[61] [7:0] $end
     $var wire 8 a" mem[62] [7:0] $end
     $var wire 8 b" mem[63] [7:0] $end
     $var wire 7 c" wr_ptr [6:0] $end
    $upscope $end
   $upscope $end
   $scope module g_lane[3] $end
    $var wire 1 : busy $end
    $scope module u_fifo $end
     $var wire 32 N# WIDTH [31:0] $end
     $var wire 32 O# DEPTH [31:0] $end
     $var wire 1 d" clk $end
     $var wire 1 e" rst_n $end
     $var wire 1 f" push $end
     $var wire 8 g" din [7:0] $end
     $var wire 8 h" dout [7:0] $end
     $var wire 1 i" full $end
     $var wire 32 P# AW [31:0] $end
     $var wire 8 j" mem[0] [7:0] $end
     $var wire 8 k" mem[1] [7:0] $end
     $var wire 8 l" mem[2] [7:0] $end
     $var wire 8 m" mem[3] [7:0] $end
     $var wire 8 n" mem[4] [7:0] $end
     $var wire 8 o" mem[5] [7:0] $end
     $var wire 8 p" mem[6] [7:0] $end
     $var wire 8 q" mem[7] [7:0] $end
     $var wire 8 r" mem[8] [7:0] $end
     $var wire 8 s" mem[9] [7:0] $end
     $var wire 8 t" mem[10] [7:0] $end
     $var wire 8 u" mem[11] [7:0] $end
     $var wire 8 v" mem[12] [7:0] $end
     $var wire 8 w" mem[13] [7:0] $end
     $var wire 8 x" mem[14] [7:0] $end
     $var wire 8 y" mem[15] [7:0] $end
     $var wire 8 z" mem[16] [7:0] $end
     $var wire 8 {" mem[17] [7:0] $end
     $var wire 8 |" mem[18] [7:0] $end
     $var wire 8 }" mem[19] [7:0] $end
     $var wire 8 ~" mem[20] [7:0] $end
     $var wire 8 !# mem[21] [7:0] $end
     $var wire 8 "# mem[22] [7:0] $end
     $var wire 8 ## mem[23] [7:0] $end
     $var wire 8 $# mem[24] [7:0] $end
     $var wire 8 %# mem[25] [7:0] $end
     $var wire 8 &# mem[26] [7:0] $end
     $var wire 8 '# mem[27] [7:0] $end
     $var wire 8 (# mem[28] [7:0] $end
     $var wire 8 )# mem[29] [7:0] $end
     $var wire 8 *# mem[30] [7:0] $end
     $var wire 8 +# mem[31] [7:0] $end
     $var wire 8 ,# mem[32] [7:0] $end
     $var wire 8 -# mem[33] [7:0] $end
     $var wire 8 .# mem[34] [7:0] $end
     $var wire 8 /# mem[35] [7:0] $end
     $var wire 8 0# mem[36] [7:0] $end
     $var wire 8 1# mem[37] [7:0] $end
     $var wire 8 2# mem[38] [7:0] $end
     $var wire 8 3# mem[39] [7:0] $end
     $var wire 8 4# mem[40] [7:0] $end
     $var wire 8 5# mem[41] [7:0] $end
     $var wire 8 6# mem[42] [7:0] $end
     $var wire 8 7# mem[43] [7:0] $end
     $var wire 8 8# mem[44] [7:0] $end
     $var wire 8 9# mem[45] [7:0] $end
     $var wire 8 :# mem[46] [7:0] $end
     $var wire 8 ;# mem[47] [7:0] $end
     $var wire 8 <# mem[48] [7:0] $end
     $var wire 8 =# mem[49] [7:0] $end
     $var wire 8 ># mem[50] [7:0] $end
     $var wire 8 ?# mem[51] [7:0] $end
     $var wire 8 @# mem[52] [7:0] $end
     $var wire 8 A# mem[53] [7:0] $end
     $var wire 8 B# mem[54] [7:0] $end
     $var wire 8 C# mem[55] [7:0] $end
     $var wire 8 D# mem[56] [7:0] $end
     $var wire 8 E# mem[57] [7:0] $end
     $var wire 8 F# mem[58] [7:0] $end
     $var wire 8 G# mem[59] [7:0] $end
     $var wire 8 H# mem[60] [7:0] $end
     $var wire 8 I# mem[61] [7:0] $end
     $var wire 8 J# mem[62] [7:0] $end
     $var wire 8 K# mem[63] [7:0] $end
     $var wire 7 L# wr_ptr [6:0] $end
    $upscope $end
   $upscope $end
  $upscope $end
  $scope module unnamedblk1 $end
   $var wire 32 * i [31:0] $end
  $upscope $end
 $upscope $end
$enddefinitions $end


#0
0#
0$
b0000 %
b00000000 &
b0000 '
b0000 (
b00000000 )
b00000000000000000000000000000000 *
0+
0,
b0000 -
b00000000 .
b0000 /
b00000000 0
b0000 1
b00000000 2
b00000000 3
b00000000 4
b00000000 5
b0000000000000000 6
07
08
09
0:
0;
0<
0=
b0000 >
0?
0@
0A
b0000 B
0C
0D
0E
b0000 F
0G
0H
0I
b0000 J
0K
0L
0M
b00000000 N
b00000000 O
0P
b00000000 Q
b00000000 R
b00000000 S
b00000000 T
b00000000 U
b00000000 V
b00000000 W
b00000000 X
b00000000 Y
b00000000 Z
b00000000 [
b00000000 \
b00000000 ]
b00000000 ^
b00000000 _
b00000000 `
b00000000 a
b00000000 b
b00000000 c
b00000000 d
b00000000 e
b00000000 f
b00000000 g
b00000000 h
b00000000 i
b00000000 j
b00000000 k
b00000000 l
b00000000 m
b00000000 n
b00000000 o
b00000000 p
b00000000 q
b00000000 r
b00000000 s
b00000000 t
b00000000 u
b00000000 v
b00000000 w
b00000000 x
b00000000 y
b00000000 z
b00000000 {
b00000000 |
b00000000 }
b00000000 ~
b00000000 !!
b00000000 "!
b00000000 #!
b00000000 $!
b00000000 %!
b00000000 &!
b00000000 '!
b00000000 (!
b00000000 )!
b00000000 *!
b00000000 +!
b00000000 ,!
b00000000 -!
b00000000 .!
b00000000 /!
b00000000 0!
b00000000 1!
b00000000 2!
b0000000 3!
04!
05!
06!
b00000000 7!
b00000000 8!
09!
b00000000 :!
b00000000 ;!
b00000000 <!
b00000000 =!
b00000000 >!
b00000000 ?!
b00000000 @!
b00000000 A!
b00000000 B!
b00000000 C!
b00000000 D!
b00000000 E!
b00000000 F!
b00000000 G!
b00000000 H!
b00000000 I!
b00000000 J!
b00000000 K!
b00000000 L!
b00000000 M!
b00000000 N!
b00000000 O!
b00000000 P!
b00000000 Q!
b00000000 R!
b00000000 S!
b00000000 T!
b00000000 U!
b00000000 V!
b00000000 W!
b00000000 X!
b00000000 Y!
b00000000 Z!
b00000000 [!
b00000000 \!
b00000000 ]!
b00000000 ^!
b00000000 _!
b00000000 `!
b00000000 a!
b00000000 b!
b00000000 c!
b00000000 d!
b00000000 e!
b00000000 f!
b00000000 g!
b00000000 h!
b00000000 i!
b00000000 j!
b00000000 k!
b00000000 l!
b00000000 m!
b00000000 n!
b00000000 o!
b00000000 p!
b00000000 q!
b00000000 r!
b00000000 s!
b00000000 t!
b00000000 u!
b00000000 v!
b00000000 w!
b00000000 x!
b00000000 y!
b0000000 z!
0{!
0|!
0}!
b00000000 ~!
b00000000 !"
0""
b00000000 #"
b00000000 $"
b00000000 %"
b00000000 &"
b00000000 '"
b00000000 ("
b00000000 )"
b00000000 *"
b00000000 +"
b00000000 ,"
b00000000 -"
b00000000 ."
b00000000 /"
b00000000 0"
b00000000 1"
b00000000 2"
b00000000 3"
b00000000 4"
b00000000 5"
b00000000 6"
b00000000 7"
b00000000 8"
b00000000 9"
b00000000 :"
b00000000 ;"
b00000000 <"
b00000000 ="
b00000000 >"
b00000000 ?"
b00000000 @"
b00000000 A"
b00000000 B"
b00000000 C"
b00000000 D"
b00000000 E"
b00000000 F"
b00000000 G"
b00000000 H"
b00000000 I"
b00000000 J"
b00000000 K"
b00000000 L"
b00000000 M"
b00000000 N"
b00000000 O"
b00000000 P"
b00000000 Q"
b00000000 R"
b00000000 S"
b00000000 T"
b00000000 U"
b00000000 V"
b00000000 W"
b00000000 X"
b00000000 Y"
b00000000 Z"
b00000000 ["
b00000000 \"
b00000000 ]"
b00000000 ^"
b00000000 _"
b00000000 `"
b00000000 a"
b00000000 b"
b0000000 c"
0d"
0e"
0f"
b00000000 g"
b00000000 h"
0i"
b00000000 j"
b00000000 k"
b00000000 l"
b00000000 m"
b00000000 n"
b00000000 o"
b00000000 p"
b00000000 q"
b00000000 r"
b00000000 s"
b00000000 t"
b00000000 u"
b00000000 v"
b00000000 w"
b00000000 x"
b00000000 y"
b00000000 z"
b00000000 {"
b00000000 |"
b00000000 }"
b00000000 ~"
b00000000 !#
b00000000 "#
b00000000 ##
b00000000 $#
b00000000 %#
b00000000 &#
b00000000 '#
b00000000 (#
b00000000 )#
b00000000 *#
b00000000 +#
b00000000 ,#
b00000000 -#
b00000000 .#
b00000000 /#
b00000000 0#
b00000000 1#
b00000000 2#
b00000000 3#
b00000000 4#
b00000000 5#
b00000000 6#
b00000000 7#
b00000000 8#
b00000000 9#
b00000000 :#
b00000000 ;#
b00000000 <#
b00000000 =#
b00000000 >#
b00000000 ?#
b00000000 @#
b00000000 A#
b00000000 B#
b00000000 C#
b00000000 D#
b00000000 E#
b00000000 F#
b00000000 G#
b00000000 H#
b00000000 I#
b00000000 J#
b00000000 K#
b0000000 L#
b00000000000000000000000000000100 M#
b00000000000000000000000000001000 N#
b00000000000000000000000001000000 O#
b00000000000000000000000000000110 P#
#5000
1#
1+
1;
1?
1C
1G
1K
14!
1{!
1d"
#10000
0#
0+
0;
0?
0C
0G
0K
04!
0{!
0d"
#15000
1#
1$
1+
1,
1;
1<
1?
1@
1C
1D
1G
1H
1K
1L
14!
15!
1{!
1|!
1d"
1e"
#20000
0#
b00010000 &
b00000000000000000000000000000001 *
0+
b00010000 .
0;
0?
0C
0G
0K
b00010000 N
04!
b00010000 7!
0{!
b00010000 ~!
0d"
b00010000 g"
#25000
1#
1+
1;
1?
1C
1G
1K
14!
1{!
1d"
#30000
0#
b0001 %
b00010001 &
b00000000000000000000000000000010 *
0+
b0001 -
b00010001 .
0;
0?
0C
0G
1I
0K
1M
b00010001 N
04!
b00010001 7!
0{!
b00010001 ~!
0d"
b00010001 g"
#35000
1#
1+
b0000000000000001 6
1;
1?
1C
1G
b0001 J
1K
b00010001 Q
b0000001 3!
14!
1{!
1d"
#40000
0#
b0010 %
b00010010 &
b00000000000000000000000000000011 *
0+
b0010 -
b00010010 .
0;
0?
0C
1E
0G
0I
0K
0M
b00010010 N
04!
16!
b00010010 7!
0{!
b00010010 ~!
0d"
b00010010 g"
#45000
1#
1+
b0000000000010001 6
1;
1?
1C
b0001 F
1G
1K
14!
b00010010 :!
b0000001 z!
1{!
1d"
#50000
0#
b0011 %
b00010011 &
b00000000000000000000000000000100 *
0+
b0011 -
b00010011 .
0;
0?
0C
0G
1I
0K
1M
b00010011 N
04!
b00010011 7!
0{!
b00010011 ~!
0d"
b00010011 g"
#55000
1#
1+
b0000000000100010 6
1;
1?
1C
b0010 F
1G
b0010 J
1K
b00010011 R
b0000010 3!
14!
b00010011 ;!
b0000010 z!
1{!
1d"
#60000
0#
b0100 %
b00010100 &
b00000000000000000000000000000101 *
0+
b0100 -
b00010100 .
0;
0?
1A
0C
0E
0G
0I
0K
0M
b00010100 N
04!
06!
b00010100 7!
0{!
1}!
b00010100 ~!
0d"
b00010100 g"
#65000
1#
1+
b0000000100100010 6
1;
1?
b0001 B
1C
1G
1K
14!
1{!
b00010100 #"
b0000001 c"
1d"
#70000
0#
b0101 %
b00010101 &
b00000000000000000000000000000110 *
0+
b0101 -
b00010101 .
0;
0?
0C
0G
1I
0K
1M
b00010101 N
04!
b00010101 7!
0{!
b00010101 ~!
0d"
b00010101 g"
#75000
1#
1+
b0000001000100011 6
1;
1?
b0010 B
1C
1G
b0011 J
1K
b00010101 S
b0000011 3!
14!
1{!
b00010101 $"
b0000010 c"
1d"
#80000
0#
b0110 %
b00010110 &
b00000000000000000000000000000111 *
0+
b0110 -
b00010110 .
0;
0?
0C
1E
0G
0I
0K
0M
b00010110 N
04!
16!
b00010110 7!
0{!
b00010110 ~!
0d"
b00010110 g"
#85000
1#
1+
b0000001100110011 6
1;
1?
b0011 B
1C
b0011 F
1G
1K
14!
b00010110 <!
b0000011 z!
1{!
b00010110 %"
b0000011 c"
1d"
#90000
0#
b0111 %
b00010111 &
b00000000000000000000000000001000 *
0+
b0111 -
b00010111 .
0;
0?
0C
0G
1I
0K
1M
b00010111 N
04!
b00010111 7!
0{!
b00010111 ~!
0d"
b00010111 g"
#95000
1#
1+
b0000010001000100 6
1;
1?
b0100 B
1C
b0100 F
1G
b0100 J
1K
b00010111 T
b0000100 3!
14!
b00010111 =!
b0000100 z!
1{!
b00010111 &"
b0000100 c"
1d"
#100000
0#
b1000 %
b00011000 &
b00000000000000000000000000001001 *
0+
b1000 -
b00011000 .
0;
1=
0?
0A
0C
0E
0G
0I
0K
0M
b00011000 N
04!
06!
b00011000 7!
0{!
0}!
b00011000 ~!
0d"
1f"
b00011000 g"
#105000
1#
1+
b0001010001000100 6
1;
b0001 >
1?
1C
1G
1K
14!
1{!
1d"
b00011000 j"
b0000001 L#
#110000
0#
b1001 %
b00011001 &
b00000000000000000000000000001010 *
0+
b1001 -
b00011001 .
0;
0?
0C
0G
1I
0K
1M
b00011001 N
04!
b00011001 7!
0{!
b00011001 ~!
0d"
b00011001 g"
#115000
1#
1+
b0010010001000101 6
1;
b0010 >
1?
1C
1G
b0101 J
1K
b00011001 U
b0000101 3!
14!
1{!
1d"
b00011001 k"
b0000010 L#
#120000
0#
b1010 %
b00011010 &
b00000000000000000000000000001011 *
0+
b1010 -
b00011010 .
0;
0?
0C
1E
0G
0I
0K
0M
b00011010 N
04!
16!
b00011010 7!
0{!
b00011010 ~!
0d"
b00011010 g"
#125000
1#
1+
b0011010001010101 6
1;
b0011 >
1?
1C
b0101 F
1G
1K
14!
b00011010 >!
b0000101 z!
1{!
1d"
b00011010 l"
b0000011 L#
#130000
0#
b1011 %
b00011011 &
b00000000000000000000000000001100 *
0+
b1011 -
b00011011 .
0;
0?
0C
0G
1I
0K
1M
b00011011 N
04!
b00011011 7!
0{!
b00011011 ~!
0d"
b00011011 g"
