designs/lanes/lanes.sv
// Correlation stress design: the two shapes that break naive name matching
// (§7.1) — a for-generate block and an instance array. Both produce indexed
// hierarchy in the trace (`g_lane[2].u_fifo.wr_ptr`, `u_cnt[1].q`) that only
// exists after elaboration.
`timescale 1ns / 1ps

module lane_fifo #(
    parameter int WIDTH = 8,
    parameter int DEPTH = 4
) (
    input  logic             clk,
    input  logic             rst_n,
    input  logic             push,
    input  logic [WIDTH-1:0] din,
    output logic [WIDTH-1:0] dout,
    output logic             full
);
    localparam int AW = $clog2(DEPTH);
    logic [WIDTH-1:0] mem [DEPTH];
    logic [AW:0]      wr_ptr;

    assign full = wr_ptr[AW];
    assign dout = mem[wr_ptr[AW-1:0]];

    always_ff @(posedge clk or negedge rst_n) begin
        if (!rst_n) wr_ptr <= '0;
        else if (push && !full) begin
            mem[wr_ptr[AW-1:0]] <= din;
            wr_ptr <= wr_ptr + 1'b1;
        end
    end
endmodule

// Instantiated as an array below, to exercise the `u_cnt[1].q` form.
module counter #(
    parameter int W = 4
) (
    input  logic         clk,
    input  logic         rst_n,
    input  logic         en,
    output logic [W-1:0] q
);
    always_ff @(posedge clk or negedge rst_n) begin
        if (!rst_n)   q <= '0;
        else if (en)  q <= q + 1'b1;
    end
endmodule

module lanes #(
    parameter int NLANES = 4,
    parameter int WIDTH  = 8
) (
    input  logic                     clk,
    input  logic                     rst_n,
    input  logic [NLANES-1:0]        push,
    input  logic [WIDTH-1:0]         din,
    output logic [NLANES-1:0]        full,
    output logic [WIDTH-1:0]         dout0,
    output logic [NLANES-1:0]        tick
);
    // for-generate: hierarchy becomes lanes.g_lane[i].u_fifo.*
    logic [WIDTH-1:0] lane_dout [NLANES];
    genvar i;
    generate
        for (i = 0; i < NLANES; i++) begin : g_lane
            logic busy;
            // 64 entries on purpose: deeper than Verilator's default
            // --trace-max-array of 32, so the memory only reaches the trace
            // when the mandatory flags of §4.0 are used.
            lane_fifo #(.WIDTH(WIDTH), .DEPTH(64)) u_fifo (
                .clk   (clk),
                .rst_n (rst_n),
                .push  (push[i]),
                .din   (din),
                .dout  (lane_dout[i]),
                .full  (full[i])
            );
            assign busy = full[i] & push[i];
        end
    endgenerate

    // Instance array: hierarchy becomes lanes.u_cnt[i].*. The output is one
    // packed vector, which the array splits 4 bits per instance — the idiom
    // instance arrays exist for, and the one simulators agree on.
    logic [NLANES*4-1:0] cnt_q;
    counter #(.W(4)) u_cnt [NLANES-1:0] (
        .clk   (clk),
        .rst_n (rst_n),
        .en    (push),
        .q     (cnt_q)
    );

    assign dout0 = lane_dout[0];
    generate
        for (i = 0; i < NLANES; i++) begin : g_tick
            assign tick[i] = (cnt_q[i*4 +: 4] == 4'hF);
        end
    endgenerate
endmodule

designs/lanes/tb_lanes.sv
`timescale 1ns / 1ps

module tb_lanes;
    localparam int NLANES = 4;
    localparam int WIDTH = 8;

    logic clk = 1'b0;
    logic rst_n;
    logic [NLANES-1:0] push;
    logic [WIDTH-1:0]  din;
    logic [NLANES-1:0] full, tick;
    logic [WIDTH-1:0]  dout0;

    lanes #(.NLANES(NLANES), .WIDTH(WIDTH)) dut (
        .clk(clk), .rst_n(rst_n), .push(push), .din(din),
        .full(full), .dout0(dout0), .tick(tick)
    );

    always #5 clk = ~clk;

    initial begin
        $dumpfile("dump.vcd");
        $dumpvars(0, tb_lanes);
        // Generate blocks and instance arrays put memories behind indexed
        // scopes; Icarus needs each element named explicitly.
        // Dumping unpacked-array elements needs an explicit element select,
        // which the LRM does not allow as a $dumpvars argument. Icarus accepts
        // it as an extension; slang and ModelSim reject it. Icarus predefines
        // __ICARUS__, so this stays an Icarus-only path and every other tool
        // reads the file cleanly.
`ifdef __ICARUS__
        $dumpvars(1, dut.g_lane[0].u_fifo.mem[0], dut.g_lane[1].u_fifo.mem[0]);
`endif
    end

    initial begin
        rst_n = 1'b0;
        push  = '0;
        din   = 8'h00;
        repeat (2) @(posedge clk);
        rst_n = 1'b1;

        for (int i = 0; i < 24; i++) begin
            @(negedge clk);
            push = NLANES'(i);
            din  = 8'h10 + i[7:0];
        end

        @(negedge clk);
        push = '1;
        repeat (20) @(negedge clk);
        push = '0;

        repeat (4) @(posedge clk);
        $finish;
    end
endmodule

designs/lanes/verilator_without.vcd
$version Generated by VerilatedVcd $end
$timescale 1ps $end
 $scope module $rootio $end
 $upscope $end
 $scope module tb_lanes $end
  $var wire 32 G NLANES [31:0] $end
  $var wire 32 H WIDTH [31:0] $end
  $var wire 1 B clk $end
  $var wire 1 # rst_n $end
  $var wire 4 $ push [3:0] $end
  $var wire 8 % din [7:0] $end
  $var wire 4 + full [3:0] $end
  $var wire 4 , tick [3:0] $end
  $var wire 8 - dout0 [7:0] $end
  $scope module dut $end
   $var wire 32 G NLANES [31:0] $end
   $var wire 32 H WIDTH [31:0] $end
   $var wire 1 B clk $end
   $var wire 1 # rst_n $end
   $var wire 4 $ push [3:0] $end
   $var wire 8 % din [7:0] $end
   $var wire 4 + full [3:0] $end
   $var wire 8 - dout0 [7:0] $end
   $var wire 4 , tick [3:0] $end
   $var wire 8 . lane_dout[0] [7:0] $end
   $var wire 8 / lane_dout[1] [7:0] $end
   $var wire 8 0 lane_dout[2] [7:0] $end
   $var wire 8 1 lane_dout[3] [7:0] $end
   $var wire 16 2 cnt_q [15:0] $end
   $scope module g_lane[0] $end
    $var wire 1 C busy $end
    $scope module u_fifo $end
     $var wire 32 H WIDTH [31:0] $end
     $var wire 32 I DEPTH [31:0] $end
     $var wire 1 B clk $end
     $var wire 1 # rst_n $end
     $var wire 1 & push $end
     $var wire 8 % din [7:0] $end
     $var wire 8 - dout [7:0] $end
     $var wire 1 3 full $end
     $var wire 32 J AW [31:0] $end
     $var wire 7 4 wr_ptr [6:0] $end
    $upscope $end
   $upscope $end
   $scope module g_lane[1] $end
    $var wire 1 D busy $end
    $scope module u_fifo $end
     $var wire 32 H WIDTH [31:0] $end
     $var wire 32 I DEPTH [31:0] $end
     $var wire 1 B clk $end
     $var wire 1 # rst_n $end
     $var wire 1 ' push $end
     $var wire 8 % din [7:0] $end
     $var wire 8 5 dout [7:0] $end
     $var wire 1 6 full $end
     $var wire 32 J AW [31:0] $end
     $var wire 7 7 wr_ptr [6:0] $end
    $upscope $end
   $upscope $end
   $scope module g_lane[2] $end
    $var wire 1 E busy $end
    $scope module u_fifo $end
     $var wire 32 H WIDTH [31:0] $end
     $var wire 32 I DEPTH [31:0] $end
     $var wire 1 B clk $end
     $var wire 1 # rst_n $end
     $var wire 1 ( push $end
     $var wire 8 % din [7:0] $end
     $var wire 8 8 dout [7:0] $end
     $var wire 1 9 full $end
     $var wire 32 J AW [31:0] $end
     $var wire 7 : wr_ptr [6:0] $end
    $upscope $end
   $upscope $end
   $scope module g_lane[3] $end
    $var wire 1 F busy $end
    $scope module u_fifo $end
     $var wire 32 H WIDTH [31:0] $end
     $var wire 32 I DEPTH [31:0] $end
     $var wire 1 B clk $end
     $var wire 1 # rst_n $end
     $var wire 1 ) push $end
     $var wire 8 % din [7:0] $end
     $var wire 8 ; dout [7:0] $end
     $var wire 1 < full $end
     $var wire 32 J AW [31:0] $end
     $var wire 7 = wr_ptr [6:0] $end
    $upscope $end
   $upscope $end
   $scope module u_cnt[0] $end
    $var wire 32 G W [31:0] $end
    $var wire 1 B clk $end
    $var wire 1 # rst_n $end
    $var wire 1 & en $end
    $var wire 4 > q [3:0] $end
   $upscope $end
   $scope module u_cnt[1] $end
    $var wire 32 G W [31:0] $end
    $var wire 1 B clk $end
    $var wire 1 # rst_n $end
    $var wire 1 ' en $end
    $var wire 4 ? q [3:0] $end
   $upscope $end
   $scope module u_cnt[2] $end
    $var wire 32 G W [31:0] $end
    $var wire 1 B clk $end
    $var wire 1 # rst_n $end
    $var wire 1 ( en $end
    $var wire 4 @ q [3:0] $end
   $upscope $end
   $scope module u_cnt[3] $end
    $var wire 32 G W [31:0] $end
    $var wire 1 B clk $end
    $var wire 1 # rst_n $end
    $var wire 1 ) en $end
    $var wire 4 A q [3:0] $end
   $upscope $end
  $upscope $end
  $scope module unnamedblk1 $end
   $var wire 32 * i [31:0] $end
  $upscope $end
 $upscope $end
$enddefinitions $end


#0
0#
b0000 $
b00000000 %
0&
0'
0(
0)
b00000000000000000000000000000000 *
b0000 +
b0000 ,
b00000000 -
b00000000 .
b00000000 /
b00000000 0
b00000000 1
b0000000000000000 2
03
b0000000 4
b00000000 5
06
b0000000 7
b00000000 8
09
b0000000 :
b00000000 ;
0<
b0000000 =
b0000 >
b0000 ?
b0000 @
b0000 A
0B
0C
0D
0E
0F
b00000000000000000000000000000100 G
b00000000000000000000000000001000 H
b00000000000000000000000001000000 I
b00000000000000000000000000000110 J
#5000
1B
#10000
0B
#15000
1#
1B
#20000
b00010000 %
b00000000000000000000000000000001 *
0B
#25000
1B
#30000
b0001 $
b00010001 %
1&
b00000000000000000000000000000010 *
0B
#35000
b0000000000000001 2
b0000001 4
b0001 >
1B
#40000
b0010 $
b00010010 %
0&
1'
b00000000000000000000000000000011 *
0B
#45000
b0000000000010001 2
b0000001 7
b0001 ?
1B
#50000
b0011 $
b00010011 %
1&
b00000000000000000000000000000100 *
0B
#55000
b0000000000100010 2
b0000010 4
b0000010 7
b0010 >
b0010 ?
1B
#60000
b0100 $
b00010100 %
0&
0'
1(
b00000000000000000000000000000101 *
0B
#65000
b0000000100100010 2
b0000001 :
b0001 @
1B
#70000
b0101 $
b00010101 %
1&
b00000000000000000000000000000110 *
0B
#75000
b0000001000100011 2
b0000011 4
b0000010 :
b0011 >
b0010 @
1B
#80000
b0110 $
b00010110 %
0&
1'
b00000000000000000000000000000111 *
0B
#85000
b0000001100110011 2
b0000011 7
b0000011 :
b0011 ?
b0011 @
1B
#90000
b0111 $
b00010111 %
1&
b00000000000000000000000000001000 *
0B
#95000
b0000010001000100 2
b0000100 4
b0000100 7
b0000100 :
b0100 >
b0100 ?
b0100 @
1B
#100000
b1000 $
b00011000 %
0&
0'
0(
1)
b00000000000000000000000000001001 *
0B
#105000
b0001010001000100 2
b0000001 =
b0001 A
1B
#110000
b1001 $
b00011001 %
1&
b00000000000000000000000000001010 *
0B
#115000
b0010010001000101 2
b0000101 4
b0000010 =
b0101 >
b0010 A
1B
#120000
b1010 $
b00011010 %
0&
1'
b00000000000000000000000000001011 *
0B
#125000
b0011010001010101 2
b0000101 7
b0000011 =
b0101 ?
b0011 A
1B
#130000
b1011 $
b00011011 %
1&
b00000000000000000000000000001100 *
0B
#135000
b0100010001100110 2
b0000110 4
b0000110 7
b0000100 =
b0110 >
b0110 ?
b0100 A
1B
#140000
b1100 $
b00011100 %
0&
0'
1(
b00000000000000000000000000001101 *
0B
#145000
b0101010101100110 2
b0000101 :
b0000101 =
b0101 @
b0101 A
1B
#150000
b1101 $
b00011101 %
1&
b00000000000000000000000000001110 *
0B
#155000
b0110011001100111 2
b0000111 4
b0000110 :
b0000110 =
b0111 >
b0110 @
b0110 A
1B
#160000
b1110 $
b00011110 %
0&
1'
b00000000000000000000000000001111 *
0B
#165000
b0111011101110111 2
b0000111 7
b0000111 :
b0000111 =
b0111 ?
b0111 @
b0111 A
1B
#170000
b1111 $
b00011111 %
1&
b00000000000000000000000000010000 *
0B
#175000
b1000100010001000 2
b0001000 4
b0001000 7
b0001000 :
b0001000 =
b1000 >
b1000 ?
b1000 @
b1000 A
1B
#180000
b0000 $
b00100000 %
0&
0'
0(
0)
b00000000000000000000000000010001 *
0B
#185000
1B
#190000
b0001 $
b00100001 %
1&
b00000000000000000000000000010010 *
0B
#195000
b1000100010001001 2
b0001001 4
b1001 >
1B
#200000
b0010 $
b00100010 %
0&
1'
b00000000000000000000000000010011 *
0B
#205000
b1000100010011001 2
b0001001 7
b1001 ?
1B
#210000
b0011 $
b00100011 %
1&
b00000000000000000000000000010100 *
0B
#215000
b1000100010101010 2
b0001010 4
b0001010 7
b1010 >
b1010 ?
1B
#220000
b0100 $
b00100100 %
0&
0'
1(
b00000000000000000000000000010101 *
0B
#225000
b1000100110101010 2
b0001001 :
b1001 @
1B
#230000
b0101 $
b00100101 %
1&
b00000000000000000000000000010110 *
0B
#235000
b1000101010101011 2
b0001011 4
b0001010 :
b1011 >
b1010 @
1B
#240000
b0110 $
b00100110 %
0&
1'
b00000000000000000000000000010111 *
0B
#245000
b1000101110111011 2
b0001011 7
b0001011 :
b1011 ?
b1011 @
1B
#250000
b0111 $
b00100111 %
1&
b00000000000000000000000000011000 *
0B
#255000
b1000110011001100 2
b0001100 4
b0001100 7
b0001100 :
b1100 >
b1100 ?
b1100 @
1B
#260000
b1111 $
1)
0B
#265000
b1001110111011101 2
b0001101 4
b0001101 7
b0001101 :
b0001001 =
b1101 >
b1101 ?
b1101 @
b1001 A
1B
#270000
0B
#275000
b1010111011101110 2
b0001110 4
b0001110 7
b0001110 :
b0001010 =
b1110 >
b1110 ?
b1110 @
b1010 A
1B
#280000
0B
#285000
b0111 ,
b1011111111111111 2
b0001111 4
b0001111 7
b0001111 :
b0001011 =
b1111 >
b1111 ?
b1111 @
b1011 A
1B
#290000
0B
#295000
b0000 ,
b1100000000000000 2
b0010000 4
b0010000 7
b0010000 :
b0001100 =
b0000 >
b0000 ?
b0000 @
b1100 A
1B
#300000
0B
#305000
b1101000100010001 2
b0010001 4
b0010001 7
b0010001 :
b0001101 =
b0001 >
b0001 ?
b0001 @
b1101 A
1B
#310000
0B
#315000
b1110001000100010 2
b0010010 4
b0010010 7
b0010010 :
b0001110 =
b0010 >
b0010 ?
b0010 @
b1110 A
1B
#320000
0B
#325000
b1000 ,
b1111001100110011 2
b0010011 4
b0010011 7
b0010011 :
b0001111 =
b0011 >
b0011 ?
b0011 @
b1111 A
1B
#330000
0B
#335000
b0000 ,
b0000010001000100 2
b0010100 4
b0010100 7
b0010100 :
b0010000 =
b0100 >
b0100 ?
b0100 @
b0000 A
1B
#340000
0B
#345000
b0001010101010101 2
b0010101 4
b0010101 7
b0010101 :
b0010001 =
b0101 >
b0101 ?
b0101 @
b0001 A
1B
#350000
0B
#355000
b0010011001100110 2
b0010110 4
b0010110 7
b0010110 :
b0010010 =
b0110 >
b0110 ?
b0110 @
b0010 A
1B
#360000
0B
#365000
b0011011101110111 2
b0010111 4
b0010111 7
b0010111 :
b0010011 =
b0111 >
b0111 ?
b0111 @
b0011 A
1B
#370000
0B
#375000
b0100100010001000 2
b0011000 4
b0011000 7
b0011000 :
b0010100 =
b1000 >
b1000 ?
b1000 @
b0100 A
1B
#380000
0B
#385000
b0101100110011001 2
b0011001 4
b0011001 7
b0011001 :
b0010101 =
b1001 >
b1001 ?
b1001 @
b0101 A
1B
#390000
0B
#395000
b0110101010101010 2
b0011010 4
b0011010 7
b0011010 :
b0010110 =
b1010 >
b1010 ?
b1010 @
b0110 A
1B
#400000
0B
#405000
b0111101110111011 2
b0011011 4
b0011011 7
b0011011 :
b0010111 =
b1011 >
b1011 ?
b1011 @
b0111 A
1B
#410000
0B
#415000
b1000110011001100 2
b0011100 4
b0011100 7
b0011100 :
b0011000 =
b1100 >
b1100 ?
b1100 @
b1000 A
1B
#420000
0B
#425000
b1001110111011101 2
b0011101 4
b0011101 7
b0011101 :
b0011001 =
b1101 >
b1101 ?
b1101 @
b1001 A
1B
#430000
0B
#435000
b1010111011101110 2
b0011110 4
b0011110 7
b0011110 :
b0011010 =
b1110 >
b1110 ?
b1110 @
b1010 A
1B
#440000
0B
#445000
b0111 ,
b1011111111111111 2
b0011111 4
b0011111 7
b0011111 :
b0011011 =
b1111 >
b1111 ?
b1111 @
b1011 A
1B
#450000
0B
#455000
b0000 ,
b1100000000000000 2
b0100000 4
b0100000 7
b0100000 :
b0011100 =
b0000 >
b0000 ?
b0000 @
b1100 A
1B
#460000
b0000 $
0&
0'
0(
0)
0B
