designs/axi_lite_slave/tb_axi_lite_bug.sv
`timescale 1ns / 1ps

// §14.1 reference bug. This minimal AXI4-Lite master changes AWADDR on every
// stalled cycle instead of holding the payload stable until AWREADY accepts it.
module tb_axi_lite_bug;
    logic        aclk = 1'b0;
    logic        aresetn = 1'b0;
    logic        awvalid = 1'b0;
    logic        awready = 1'b0;
    logic [31:0] awaddr = 32'h1000;
    logic [ 2:0] awprot = '0;
    logic        wvalid = 1'b0;
    logic        wready = 1'b0;
    logic [31:0] wdata = 32'hCAFE_BABE;
    logic [ 3:0] wstrb = 4'hF;
    logic        bvalid = 1'b0;
    logic        bready = 1'b1;
    logic [ 1:0] bresp = 2'b00;
    logic        arvalid = 1'b0;
    logic        arready = 1'b0;
    logic [31:0] araddr = '0;
    logic [ 2:0] arprot = '0;
    logic        rvalid = 1'b0;
    logic        rready = 1'b1;
    logic [31:0] rdata = '0;
    logic [ 1:0] rresp = 2'b00;
    logic [ 3:0] step = '0;

    always #5 aclk = ~aclk;

    always_ff @(posedge aclk or negedge aresetn) begin
        if (!aresetn) begin
            awaddr <= 32'h1000;
            step <= '0;
        end else if (awvalid && !awready) begin
            // BUG: AXI requires AWADDR to remain stable in this interval.
            step <= step + 1'b1;
            awaddr <= 32'h1000 + {26'd0, step, 2'b00};
        end
    end

    initial begin
        $dumpfile("dump.vcd");
        $dumpvars(0, tb_axi_lite_bug);
        #12 aresetn = 1'b1;
        #8 awvalid = 1'b1;
        repeat (5) @(posedge aclk);
        awready = 1'b1;
        @(posedge aclk);
        awvalid = 1'b0;
        awready = 1'b0;
        #20 $finish;
    end
endmodule

designs/axi_lite_slave/dump.vcd
$date
	Mon Aug 31 18:55:29 2026
$end
$version
	Icarus Verilog
$end
$timescale
	1ps
$end
$scope module tb_axi_lite_bug $end
$var reg 1 ! aclk $end
$var reg 32 " araddr [31:0] $end
$var reg 1 # aresetn $end
$var reg 3 $ arprot [2:0] $end
$var reg 1 % arready $end
$var reg 1 & arvalid $end
$var reg 32 ' awaddr [31:0] $end
$var reg 3 ( awprot [2:0] $end
$var reg 1 ) awready $end
$var reg 1 * awvalid $end
$var reg 1 + bready $end
$var reg 2 , bresp [1:0] $end
$var reg 1 - bvalid $end
$var reg 32 . rdata [31:0] $end
$var reg 1 / rready $end
$var reg 2 0 rresp [1:0] $end
$var reg 1 1 rvalid $end
$var reg 4 2 step [3:0] $end
$var reg 32 3 wdata [31:0] $end
$var reg 1 4 wready $end
$var reg 4 5 wstrb [3:0] $end
$var reg 1 6 wvalid $end
$upscope $end
$enddefinitions $end
$comment Show the parameter values. $end
$dumpall
$end
#0
$dumpvars
06
b1111 5
04
b11001010111111101011101010111110 3
b0 2
01
b0 0
1/
b0 .
0-
b0 ,
1+
0*
0)
b0 (
b1000000000000 '
0&
0%
b0 $
0#
b0 "
0!
$end
#5000
1!
#10000
0!
#12000
1#
#15000
1!
#20000
0!
1*
#25000
b1 2
1!
#30000
0!
#35000
b1000000000100 '
b10 2
1!
#40000
0!
#45000
b1000000001000 '
b11 2
1!
#50000
0!
#55000
b1000000001100 '
b100 2
1!
#60000
0!
#65000
b1000000010000 '
b101 2
1)
1!
#70000
0!
#75000
0)
0*
1!
