designs/fifo_buggy/fifo_buggy.sv
`timescale 1ns / 1ps

// fifo_sync with one injected bug, for the why-trace golden test.
//
// THE BUG: the read pointer is held in reset by `rd_rst_n`, which is tied low
// and never deasserted. rd_ptr therefore stays at 0, the FIFO fills and `full`
// sticks high forever. This is the §8.1 shape: a symptom several hops away from
// a signal that simply never moved.
//
// Everything else is identical to designs/fifo_async/fifo_sync.sv.
module fifo_buggy #(
    parameter int WIDTH = 8,
    parameter int DEPTH = 16
) (
    input  logic             clk,
    input  logic             rst_n,
    input  logic             wr_en,
    input  logic [WIDTH-1:0] wr_data,
    input  logic             rd_en,
    output logic [WIDTH-1:0] rd_data,
    output logic             full,
    output logic             empty
);
    localparam int ADDR_W = $clog2(DEPTH);
    logic [WIDTH-1:0] mem [DEPTH];
    logic [ADDR_W:0]  wr_ptr, rd_ptr;

    // BUG: intended as a synchronised release of the read-side reset, but the
    // deassert was never written, so it is a constant 0.
    logic rd_rst_n;
    assign rd_rst_n = 1'b0;

    assign full    = wr_ptr[ADDR_W] != rd_ptr[ADDR_W] &&
                      wr_ptr[ADDR_W-1:0] == rd_ptr[ADDR_W-1:0];
    assign empty   = wr_ptr == rd_ptr;
    assign rd_data = mem[rd_ptr[ADDR_W-1:0]];

    always_ff @(posedge clk or negedge rst_n) begin
        if (!rst_n) begin
            wr_ptr <= '0;
        end else if (wr_en && !full) begin
            mem[wr_ptr[ADDR_W-1:0]] <= wr_data;
            wr_ptr <= wr_ptr + 1'b1;
        end
    end

    always_ff @(posedge clk or negedge rd_rst_n) begin
        if (!rd_rst_n) rd_ptr <= '0;
        else if (rd_en && !empty) rd_ptr <= rd_ptr + 1'b1;
    end
endmodule

designs/fifo_buggy/tb_fifo_buggy.sv
`timescale 1ns / 1ps

// Drives fifo_buggy until the symptom appears: `full` goes high and never
// clears, even though reads are requested continuously.
module tb_fifo_buggy;
    localparam int WIDTH = 8;
    localparam int DEPTH = 16;

    logic             clk = 1'b0;
    logic             rst_n;
    logic             wr_en, rd_en;
    logic [WIDTH-1:0] wr_data;
    logic [WIDTH-1:0] rd_data;
    logic             full, empty;

    fifo_buggy #(.WIDTH(WIDTH), .DEPTH(DEPTH)) dut (
        .clk(clk), .rst_n(rst_n),
        .wr_en(wr_en), .wr_data(wr_data),
        .rd_en(rd_en), .rd_data(rd_data),
        .full(full), .empty(empty)
    );

    always #5 clk = ~clk;

    // A liveness check, of the shape a real testbench has: once reads are
    // being requested, the FIFO must drain. With the injected bug it never
    // does, so this fires repeatedly and fills the log — which is what
    // `veritrace triage` is given (§8.10b).
    //
    // The message is deliberately in the ordinary "assertion ... failed at
    // time ..." shape, so the default patterns of §8.10b recognise it with no
    // configuration. `$time` is in this module's time unit, hence the `ns`.
    int stall;
    always @(posedge clk) begin
        if (!rst_n) begin
            stall <= 0;
        end else if (rd_en && full) begin
            stall <= stall + 1;
            if (stall > 4) begin
                $display("ERROR: assertion \"p_fifo_drains\" failed at time %0dns", $time);
                $display("       tb_fifo_buggy.dut.full");
            end
        end else begin
            stall <= 0;
        end
    end

    initial begin
        $dumpfile("dump.vcd");
        $dumpvars(0, tb_fifo_buggy);
        // Dumping unpacked-array elements needs an explicit element select,
        // which the LRM does not allow as a $dumpvars argument. Icarus accepts
        // it as an extension; slang and ModelSim reject it. Icarus predefines
        // __ICARUS__, so this stays an Icarus-only path and every other tool
        // reads the file cleanly.
`ifdef __ICARUS__
        $dumpvars(1, dut.mem[0], dut.mem[1]);
`endif
    end

    initial begin
        rst_n   = 1'b0;
        wr_en   = 1'b0;
        rd_en   = 1'b0;
        wr_data = '0;
        repeat (2) @(posedge clk);
        rst_n = 1'b1;

        // Fill it.
        for (int i = 0; i < DEPTH + 4; i++) begin
            @(negedge clk);
            wr_en   = 1'b1;
            wr_data = 8'h20 + i[7:0];
        end

        // Ask for reads that will never be honoured: rd_ptr is stuck in reset,
        // so `full` stays high from here to the end of the run.
        @(negedge clk);
        wr_en = 1'b0;
        rd_en = 1'b1;
        repeat (20) @(negedge clk);

        repeat (4) @(posedge clk);
        $finish;
    end
endmodule

designs/fifo_buggy/dump.vcd
$date
	Mon Aug 03 17:25:46 2026
$end
$version
	Icarus Verilog
$end
$timescale
	1ps
$end
$scope module tb_fifo_buggy $end
$var wire 8 ! rd_data [7:0] $end
$var wire 1 " full $end
$var wire 1 # empty $end
$var parameter 32 $ DEPTH $end
$var parameter 32 % WIDTH $end
$var reg 1 & clk $end
$var reg 1 ' rd_en $end
$var reg 1 ( rst_n $end
$var reg 8 ) wr_data [7:0] $end
$var reg 1 * wr_en $end
$var integer 32 + stall [31:0] $end
$scope module dut $end
$var wire 1 & clk $end
$var wire 1 " full $end
$var wire 8 , rd_data [7:0] $end
$var wire 1 ' rd_en $end
$var wire 1 - rd_rst_n $end
$var wire 1 ( rst_n $end
$var wire 8 . wr_data [7:0] $end
$var wire 1 * wr_en $end
$var wire 1 # empty $end
$var parameter 32 / ADDR_W $end
$var parameter 32 0 DEPTH $end
$var parameter 32 1 WIDTH $end
$var reg 5 2 rd_ptr [4:0] $end
$var reg 5 3 wr_ptr [4:0] $end
$upscope $end
$scope begin $ivl_for_loop0 $end
$var integer 32 4 i [31:0] $end
$upscope $end
$upscope $end
$scope module tb_fifo_buggy $end
$scope module dut $end
$var reg 8 5 \mem[0] [7:0] $end
$upscope $end
$upscope $end
$scope module tb_fifo_buggy $end
$scope module dut $end
$var reg 8 6 \mem[1] [7:0] $end
$upscope $end
$upscope $end
$enddefinitions $end
$comment Show the parameter values. $end
$dumpall
b1000 1
b10000 0
b100 /
b1000 %
b10000 $
$end
#0
$dumpvars
bx 6
bx 5
b0 4
b0 3
bx 2
b0 .
0-
bx ,
b0 +
0*
b0 )
0(
0'
0&
x#
x"
bx !
$end
#5000
0"
1#
b0 2
1&
#10000
0&
#15000
1(
1&
#20000
b1 4
b100000 )
b100000 .
1*
0&
#25000
0#
b1 3
b100000 5
b100000 !
b100000 ,
1&
#30000
b10 4
b100001 )
b100001 .
0&
#35000
b10 3
b100001 6
1&
#40000
b11 4
b100010 )
b100010 .
0&
#45000
b11 3
1&
#50000
b100 4
b100011 )
b100011 .
0&
#55000
b100 3
1&
#60000
b101 4
b100100 )
b100100 .
0&
#65000
b101 3
1&
#70000
b110 4
b100101 )
b100101 .
0&
#75000
b110 3
1&
#80000
b111 4
b100110 )
b100110 .
0&
#85000
b111 3
1&
#90000
b1000 4
b100111 )
b100111 .
0&
#95000
b1000 3
1&
#100000
b1001 4
b101000 )
b101000 .
0&
#105000
b1001 3
1&
#110000
b1010 4
b101001 )
b101001 .
0&
#115000
b1010 3
1&
#120000
b1011 4
b101010 )
b101010 .
0&
#125000
b1011 3
1&
#130000
b1100 4
b101011 )
b101011 .
0&
#135000
b1100 3
1&
#140000
b1101 4
b101100 )
b101100 .
0&
#145000
b1101 3
1&
#150000
b1110 4
b101101 )
b101101 .
0&
#155000
b1110 3
1&
#160000
b1111 4
b101110 )
b101110 .
0&
#165000
b1111 3
1&
#170000
b10000 4
b101111 )
b101111 .
0&
#175000
1"
b10000 3
1&
#180000
b10001 4
b110000 )
b110000 .
0&
#185000
1&
#190000
b10010 4
b110001 )
b110001 .
0&
#195000
1&
#200000
b10011 4
b110010 )
b110010 .
0&
#205000
1&
#210000
b10100 4
b110011 )
b110011 .
0&
#215000
1&
#220000
1'
0*
0&
#225000
b1 +
1&
#230000
0&
#235000
b10 +
1&
#240000
0&
#245000
b11 +
1&
#250000
0&
#255000
b100 +
1&
#260000
0&
#265000
b101 +
1&
#270000
0&
#275000
b110 +
1&
#280000
0&
#285000
b111 +
1&
#290000
0&
#295000
b1000 +
1&
#300000
0&
#305000
b1001 +
1&
#310000
0&
#315000
b1010 +
1&
#320000
0&
#325000
b1011 +
1&
#330000
0&
#335000
b1100 +
1&
#340000
0&
#345000
b1101 +
1&
#350000
0&
#355000
b1110 +
1&
#360000
0&
#365000
b1111 +
1&
#370000
0&
#375000
b10000 +
1&
#380000
0&
#385000
b10001 +
1&
#390000
0&
#395000
b10010 +
1&
#400000
0&
#405000
b10011 +
1&
#410000
0&
#415000
b10100 +
1&
#420000
0&
#425000
b10101 +
1&
#430000
0&
#435000
b10110 +
1&
#440000
0&
#445000
b10111 +
1&
#450000
0&
#455000
b11000 +
1&
