designs/fifo_async/fifo_sync.sv
`timescale 1ns / 1ps

module fifo_sync #(
    parameter int WIDTH = 8,
    parameter int DEPTH = 16
) (
    input  logic             clk,
    input  logic             rst_n,
    input  logic             wr_en,
    input  logic [WIDTH-1:0] wr_data,
    input  logic             rd_en,
    output logic [WIDTH-1:0] rd_data,
    output logic             full,
    output logic             empty
);
    localparam int ADDR_W = $clog2(DEPTH);
    logic [WIDTH-1:0] mem [DEPTH];
    logic [ADDR_W:0]  wr_ptr, rd_ptr;
    assign full    = wr_ptr[ADDR_W] != rd_ptr[ADDR_W] &&
                      wr_ptr[ADDR_W-1:0] == rd_ptr[ADDR_W-1:0];
    assign empty   = wr_ptr == rd_ptr;
    assign rd_data = mem[rd_ptr[ADDR_W-1:0]];

    always_ff @(posedge clk or negedge rst_n) begin
        if (!rst_n) begin
            wr_ptr <= '0;
            rd_ptr <= '0;
        end else begin
            if (wr_en && !full) begin
                mem[wr_ptr[ADDR_W-1:0]] <= wr_data;
                wr_ptr <= wr_ptr + 1'b1;
            end
            if (rd_en && !empty) rd_ptr <= rd_ptr + 1'b1;
        end
    end
endmodule

designs/fifo_async/tb_fifo_sync.sv
`timescale 1ns / 1ps

// Testbench for fifo_sync. Deliberately exercises the cases the trace core
// has to get right: X values before reset, combinational settling (full/empty
// glitch on the same timestamp as a pointer update), and array elements that
// only appear in the dump when named explicitly (§5.6).
module tb_fifo_sync;
    localparam int WIDTH = 8;
    localparam int DEPTH = 16;

    logic             clk = 1'b0;
    logic             rst_n;
    logic             wr_en, rd_en;
    logic [WIDTH-1:0] wr_data;
    logic [WIDTH-1:0] rd_data;
    logic             full, empty;

    fifo_sync #(.WIDTH(WIDTH), .DEPTH(DEPTH)) dut (
        .clk(clk), .rst_n(rst_n),
        .wr_en(wr_en), .wr_data(wr_data),
        .rd_en(rd_en), .rd_data(rd_data),
        .full(full), .empty(empty)
    );

    always #5 clk = ~clk;

    initial begin
        $dumpfile("dump.vcd");
        $dumpvars(0, tb_fifo_sync);
        // Dumping unpacked-array elements needs an explicit element select,
        // which the LRM does not allow as a $dumpvars argument. Icarus accepts
        // it as an extension; slang and ModelSim reject it. Icarus predefines
        // __ICARUS__, so this stays an Icarus-only path and every other tool
        // reads the file cleanly.
`ifdef __ICARUS__
        $dumpvars(1, dut.mem[0], dut.mem[1], dut.mem[2], dut.mem[3]);
`endif
    end

    initial begin
        rst_n   = 1'b0;
        wr_en   = 1'b0;
        rd_en   = 1'b0;
        wr_data = '0;
        repeat (2) @(posedge clk);
        rst_n = 1'b1;

        // Fill past full to exercise the full flag.
        for (int i = 0; i < DEPTH + 2; i++) begin
            @(negedge clk);
            wr_en   = 1'b1;
            wr_data = 8'hA0 + i[7:0];
        end
        @(negedge clk);
        wr_en = 1'b0;

        // Drain past empty to exercise the empty flag.
        for (int i = 0; i < DEPTH + 2; i++) begin
            @(negedge clk);
            rd_en = 1'b1;
        end
        @(negedge clk);
        rd_en = 1'b0;

        // Simultaneous read+write, and back-to-back single-cycle pulses.
        repeat (4) begin
            @(negedge clk);
            wr_en   = 1'b1;
            rd_en   = 1'b1;
            wr_data = wr_data + 8'h11;
        end
        @(negedge clk);
        wr_en = 1'b0;
        rd_en = 1'b0;

        repeat (4) @(posedge clk);
        $finish;
    end
endmodule

designs/fifo_async/dump.vcd
$date
	Mon Aug 03 17:25:46 2026
$end
$version
	Icarus Verilog
$end
$timescale
	1ps
$end
$scope module tb_fifo_sync $end
$var wire 8 ! rd_data [7:0] $end
$var wire 1 " full $end
$var wire 1 # empty $end
$var parameter 32 $ DEPTH $end
$var parameter 32 % WIDTH $end
$var reg 1 & clk $end
$var reg 1 ' rd_en $end
$var reg 1 ( rst_n $end
$var reg 8 ) wr_data [7:0] $end
$var reg 1 * wr_en $end
$scope module dut $end
$var wire 1 & clk $end
$var wire 1 " full $end
$var wire 8 + rd_data [7:0] $end
$var wire 1 ' rd_en $end
$var wire 1 ( rst_n $end
$var wire 8 , wr_data [7:0] $end
$var wire 1 * wr_en $end
$var wire 1 # empty $end
$var parameter 32 - ADDR_W $end
$var parameter 32 . DEPTH $end
$var parameter 32 / WIDTH $end
$var reg 5 0 rd_ptr [4:0] $end
$var reg 5 1 wr_ptr [4:0] $end
$upscope $end
$scope begin $ivl_for_loop0 $end
$var integer 32 2 i [31:0] $end
$upscope $end
$scope begin $ivl_for_loop1 $end
$var integer 32 3 i [31:0] $end
$upscope $end
$upscope $end
$scope module tb_fifo_sync $end
$scope module dut $end
$var reg 8 4 \mem[0] [7:0] $end
$upscope $end
$upscope $end
$scope module tb_fifo_sync $end
$scope module dut $end
$var reg 8 5 \mem[1] [7:0] $end
$upscope $end
$upscope $end
$scope module tb_fifo_sync $end
$scope module dut $end
$var reg 8 6 \mem[2] [7:0] $end
$upscope $end
$upscope $end
$scope module tb_fifo_sync $end
$scope module dut $end
$var reg 8 7 \mem[3] [7:0] $end
$upscope $end
$upscope $end
$enddefinitions $end
$comment Show the parameter values. $end
$dumpall
b1000 /
b10000 .
b100 -
b1000 %
b10000 $
$end
#0
$dumpvars
bx 7
bx 6
bx 5
bx 4
b0 3
b0 2
b0 1
b0 0
b0 ,
bx +
0*
b0 )
0(
0'
0&
1#
0"
bx !
$end
#5000
1&
#10000
0&
#15000
1(
1&
#20000
b1 2
b10100000 )
b10100000 ,
1*
0&
#25000
0#
b1 1
b10100000 4
b10100000 !
b10100000 +
1&
#30000
b10 2
b10100001 )
b10100001 ,
0&
#35000
b10 1
b10100001 5
1&
#40000
b11 2
b10100010 )
b10100010 ,
0&
#45000
b11 1
b10100010 6
1&
#50000
b100 2
b10100011 )
b10100011 ,
0&
#55000
b100 1
b10100011 7
1&
#60000
b101 2
b10100100 )
b10100100 ,
0&
#65000
b101 1
1&
#70000
b110 2
b10100101 )
b10100101 ,
0&
#75000
b110 1
1&
#80000
b111 2
b10100110 )
b10100110 ,
0&
#85000
b111 1
1&
#90000
b1000 2
b10100111 )
b10100111 ,
0&
#95000
b1000 1
1&
#100000
b1001 2
b10101000 )
b10101000 ,
0&
#105000
b1001 1
1&
#110000
b1010 2
b10101001 )
b10101001 ,
0&
#115000
b1010 1
1&
#120000
b1011 2
b10101010 )
b10101010 ,
0&
#125000
b1011 1
1&
#130000
b1100 2
b10101011 )
b10101011 ,
0&
#135000
b1100 1
1&
#140000
b1101 2
b10101100 )
b10101100 ,
0&
#145000
b1101 1
1&
#150000
b1110 2
b10101101 )
b10101101 ,
0&
#155000
b1110 1
1&
#160000
b1111 2
b10101110 )
b10101110 ,
0&
#165000
b1111 1
1&
#170000
b10000 2
b10101111 )
b10101111 ,
0&
#175000
1"
b10000 1
1&
#180000
b10001 2
b10110000 )
b10110000 ,
0&
#185000
1&
#190000
b10010 2
b10110001 )
b10110001 ,
0&
#195000
1&
#200000
0*
0&
#205000
1&
#210000
b1 3
1'
0&
#215000
0"
b10100001 !
b10100001 +
b1 0
1&
#220000
b10 3
0&
#225000
b10100010 !
b10100010 +
b10 0
1&
#230000
b11 3
0&
#235000
b10100011 !
b10100011 +
b11 0
1&
#240000
b100 3
0&
#245000
b10100100 !
b10100100 +
b100 0
1&
#250000
b101 3
0&
#255000
b10100101 !
b10100101 +
b101 0
1&
#260000
b110 3
0&
#265000
b10100110 !
b10100110 +
b110 0
1&
#270000
b111 3
0&
#275000
b10100111 !
b10100111 +
b111 0
1&
#280000
b1000 3
0&
#285000
b10101000 !
b10101000 +
b1000 0
1&
#290000
b1001 3
0&
#295000
b10101001 !
b10101001 +
b1001 0
1&
#300000
b1010 3
0&
#305000
b10101010 !
b10101010 +
b1010 0
1&
#310000
b1011 3
0&
#315000
b10101011 !
b10101011 +
b1011 0
1&
#320000
b1100 3
0&
#325000
b10101100 !
b10101100 +
b1100 0
1&
#330000
b1101 3
0&
#335000
b10101101 !
b10101101 +
b1101 0
1&
#340000
b1110 3
0&
#345000
b10101110 !
b10101110 +
b1110 0
1&
#350000
b1111 3
0&
#355000
b10101111 !
b10101111 +
b1111 0
1&
#360000
b10000 3
0&
#365000
0"
b10100000 !
b10100000 +
1#
b10000 0
1&
#370000
b10001 3
0&
#375000
1&
#380000
b10010 3
0&
#385000
1&
#390000
0'
0&
#395000
1&
#400000
b11000010 )
b11000010 ,
1'
1*
0&
#405000
0#
b10001 1
b11000010 4
b11000010 !
b11000010 +
1&
#410000
b11010011 )
b11010011 ,
0&
#415000
b11010011 !
b11010011 +
b10001 0
b10010 1
b11010011 5
1&
#420000
b11100100 )
b11100100 ,
0&
#425000
b11100100 !
b11100100 +
b10010 0
b10011 1
b11100100 6
1&
#430000
b11110101 )
b11110101 ,
0&
#435000
b11110101 !
b11110101 +
b10011 0
b10100 1
b11110101 7
1&
#440000
0'
0*
0&
