designs/handshake/handshake.sv
`timescale 1ns / 1ps

// §8.9's structural row: a `ready` that is a function of `valid` in the same
// cycle. Two AXI4-Lite-ish channels, built from one source:
//
//   * `s_axi_awready` is registered — the correct shape;
//   * `s_axi_wready`  is combinational *from wvalid* — the deadlock risk.
//
// The point of the design is that **the trace shows nothing**. Both channels
// complete every transfer in this run, because the master never waits on ready
// before asserting valid. The day the other side does, `wready` and `wvalid`
// wait for each other forever. A structural check finds it; no amount of
// simulation on this stimulus will.
module handshake_dut (
    input  logic clk,
    input  logic rst_n,

    input  logic s_axi_awvalid,
    output logic s_axi_awready,
    input  logic [31:0] s_axi_awaddr,

    input  logic s_axi_wvalid,
    output logic s_axi_wready,
    input  logic [31:0] s_axi_wdata,

    output logic s_axi_bvalid,
    input  logic s_axi_bready,

    input  logic s_axi_arvalid,
    output logic s_axi_arready,
    input  logic [31:0] s_axi_araddr,

    output logic s_axi_rvalid,
    input  logic s_axi_rready,
    output logic [31:0] s_axi_rdata
);
    logic busy;

    // Correct: ready comes out of a flop, so it cannot depend on this cycle's
    // valid however the logic is written.
    always_ff @(posedge clk or negedge rst_n) begin
        if (!rst_n) s_axi_awready <= 1'b0;
        else        s_axi_awready <= ~busy;
    end

`ifdef FIX_HANDSHAKE
    assign s_axi_wready = ~busy;
`else
    // The bug: wready is a combinational function of wvalid. Legal Verilog,
    // simulates fine here, and a deadlock against any master that waits for
    // ready before raising valid.
    assign s_axi_wready = s_axi_wvalid & ~busy;
`endif

    always_ff @(posedge clk or negedge rst_n) begin
        if (!rst_n) begin
            busy         <= 1'b0;
            s_axi_bvalid <= 1'b0;
            s_axi_rvalid <= 1'b0;
            s_axi_rdata  <= 32'd0;
        end else begin
            busy <= s_axi_awvalid & s_axi_awready;
            s_axi_bvalid <= (s_axi_wvalid & s_axi_wready) ? 1'b1
                          : (s_axi_bvalid & s_axi_bready) ? 1'b0 : s_axi_bvalid;
            s_axi_rvalid <= (s_axi_arvalid & s_axi_arready) ? 1'b1
                          : (s_axi_rvalid & s_axi_rready) ? 1'b0 : s_axi_rvalid;
            if (s_axi_arvalid & s_axi_arready) s_axi_rdata <= s_axi_araddr;
        end
    end

    assign s_axi_arready = ~s_axi_rvalid;
endmodule

module tb_handshake;
    logic clk = 1'b0, rst_n = 1'b0;
    logic awvalid = 0, wvalid = 0, bready = 1, arvalid = 0, rready = 1;
    logic awready, wready, bvalid, arready, rvalid;
    logic [31:0] awaddr = 32'h40, wdata = 32'hA5, araddr = 32'h40, rdata;

    handshake_dut dut (
        .clk(clk), .rst_n(rst_n),
        .s_axi_awvalid(awvalid), .s_axi_awready(awready), .s_axi_awaddr(awaddr),
        .s_axi_wvalid(wvalid), .s_axi_wready(wready), .s_axi_wdata(wdata),
        .s_axi_bvalid(bvalid), .s_axi_bready(bready),
        .s_axi_arvalid(arvalid), .s_axi_arready(arready), .s_axi_araddr(araddr),
        .s_axi_rvalid(rvalid), .s_axi_rready(rready), .s_axi_rdata(rdata)
    );

    always #5 clk = ~clk;

    initial begin
        $dumpfile("dump.vcd");
        $dumpvars(0, tb_handshake);
        #12 rst_n = 1'b1;
        // A master that raises valid without waiting: every transfer completes,
        // and the combinational path never shows itself.
        repeat (4) begin
            @(posedge clk) awvalid <= 1'b1;
            @(posedge clk) awvalid <= 1'b0; wvalid <= 1'b1;
            @(posedge clk) wvalid <= 1'b0;
            @(posedge clk) arvalid <= 1'b1;
            @(posedge clk) arvalid <= 1'b0;
        end
        #40 $finish;
    end
endmodule

designs/handshake/dump.vcd
$date
	Sat Aug 15 11:18:40 2026
$end
$version
	Icarus Verilog
$end
$timescale
	1ps
$end
$scope module tb_handshake $end
$var wire 1 ! wready $end
$var wire 1 " rvalid $end
$var wire 32 # rdata [31:0] $end
$var wire 1 $ bvalid $end
$var wire 1 % awready $end
$var wire 1 & arready $end
$var reg 32 ' araddr [31:0] $end
$var reg 1 ( arvalid $end
$var reg 32 ) awaddr [31:0] $end
$var reg 1 * awvalid $end
$var reg 1 + bready $end
$var reg 1 , clk $end
$var reg 1 - rready $end
$var reg 1 . rst_n $end
$var reg 32 / wdata [31:0] $end
$var reg 1 0 wvalid $end
$scope module dut $end
$var wire 1 , clk $end
$var wire 1 . rst_n $end
$var wire 32 1 s_axi_araddr [31:0] $end
$var wire 1 & s_axi_arready $end
$var wire 1 ( s_axi_arvalid $end
$var wire 32 2 s_axi_awaddr [31:0] $end
$var wire 1 * s_axi_awvalid $end
$var wire 1 + s_axi_bready $end
$var wire 1 - s_axi_rready $end
$var wire 32 3 s_axi_wdata [31:0] $end
$var wire 1 ! s_axi_wready $end
$var wire 1 0 s_axi_wvalid $end
$var reg 1 4 busy $end
$var reg 1 % s_axi_awready $end
$var reg 1 $ s_axi_bvalid $end
$var reg 32 5 s_axi_rdata [31:0] $end
$var reg 1 " s_axi_rvalid $end
$upscope $end
$upscope $end
$enddefinitions $end
$comment Show the parameter values. $end
$dumpall
$end
#0
$dumpvars
bx 5
x4
b10100101 3
b1000000 2
b1000000 1
00
b10100101 /
0.
1-
0,
1+
0*
b1000000 )
0(
b1000000 '
x&
x%
x$
bx #
x"
0!
$end
#5000
1&
0%
b0 #
b0 5
0"
0$
04
1,
#10000
0,
#12000
1.
#15000
1%
1*
1,
#20000
0,
#25000
0!
14
10
0*
1,
#30000
0,
#35000
04
0%
00
1,
#40000
0,
#45000
1%
1(
1,
#50000
0,
#55000
0&
b1000000 #
b1000000 5
1"
0(
1,
#60000
0,
#65000
1&
0"
1*
1,
#70000
0,
#75000
0!
14
10
0*
1,
#80000
0,
#85000
0%
04
00
1,
#90000
0,
#95000
1%
1(
1,
#100000
0,
#105000
0&
1"
0(
1,
#110000
0,
#115000
1&
0"
1*
1,
#120000
0,
#125000
0!
14
10
0*
1,
#130000
0,
#135000
04
0%
00
1,
#140000
0,
#145000
1%
1(
1,
#150000
0,
#155000
0&
1"
0(
1,
#160000
0,
#165000
1&
0"
1*
1,
#170000
0,
#175000
0!
14
10
0*
1,
#180000
0,
#185000
0%
04
00
1,
#190000
0,
#195000
1%
1(
1,
#200000
0,
#205000
0&
1"
0(
1,
#210000
0,
#215000
1&
0"
1,
